Workbook

Sheet Raw Data
C9: C1 | D9: C2 | E9: C3 | F9: C4 | G9: C5 | H9: C6 | I9: C7 | J9: C8 | K9: C9 | L9: C10 | M9: C11 | N9: C12
C10: YYQXXX-Bidding | D10: Project Management | E10: Common of Project | F10: 703430 | G10: Insurance premium - Property (Project) | H10: Direct Cost | I10: Expense | J10: General Expense | K10: X | L10: 1 | M10: 1 | N10: 1
C11: YYQXXX-Bidding | D11: Project Management | E11: Common of Project | F11: 703852 | G11: Stamp Duty & BG | H11: Direct Cost | I11: Expense | J11: General Expense | L11: 0 | M11: 0 | N11: 0
C12: YYQXXX-Bidding | D12: Project Management | E12: Common of Project | F12: 706700-F/M&Below | G12: Unit rate allocation (Only Construction) | H12: Indirect Cost | I12: TNS Labor | J12: TNS Labor Direct | L12: 0 | M12: 0 | N12: 0
C13: YYQXXX-Bidding | D13: Project Management | E13: Common of Project | F13: 706700-S/V&Above | G13: Unit rate allocation | H13: Indirect Cost | I13: TNS Labor | J13: TNS Labor Indirect | K13: X | L13: 554935.55 | M13: 0 | N13: 0
C14: YYQXXX-Bidding | D14: Project Management | E14: Common of Project | F14: Allowance - Indirect | G14: Indirect Allowance | H14: Indirect Cost | I14: Allowance | J14: Allowance | L14: 0 | M14: 0 | N14: 0
C15: YYQXXX-Bidding | D15: Project Management | E15: Common of Project | F15: Contingency - Direct | G15: Direct Contingency | H15: Direct Cost | I15: Contingency | J15: Contingency | K15: X | L15: 1 | M15: 1 | N15: 1
C16: YYQXXX-Bidding | D16: Project Management | E16: Common of Project | F16: Contingency - Indirect | G16: Indirect Contingency | H16: Indirect Cost | I16: Contingency | J16: Contingency | L16: 0 | M16: 0 | N16: 0
C17: YYQXXX-Bidding | D17: Project Management | E17: Common of Project | F17: Cost Impact - Direct | G17: Direct Cost Impact | H17: Direct Cost | I17: Cost Impact | J17: Cost Impact | L17: 0 | M17: 0 | N17: 0
C18: YYQXXX-Bidding | D18: Project Management | E18: Common of Project | F18: Cost Impact - Indirect | G18: Indirect Cost Impact | H18: Indirect Cost | I18: Cost Impact | J18: Cost Impact | K18: X | L18: 1 | M18: 1 | N18: 1
C19: YYQXXX-Bidding | D19: Project Management | E19: Common of Project | F19: Other - Indirect | G19: Indirect Other | H19: Indirect Cost | I19: Other | J19: Other | L19: 0 | M19: 0 | N19: 0
C20: YYQCXXX | D20: Construction | E20: Common of Project | F20: 701000 | G20: Material Cost | H20: Direct Cost | I20: Materials | J20: Permanent Material | L20: 0 | M20: 0 | N20: 0
C21: YYQCXXX | D21: Construction | E21: Common of Project | F21: 701008 | G21: Procurement contingency for Materials | H21: Direct Cost | I21: Materials | J21: Permanent Material | L21: 0 | M21: 0 | N21: 0
C22: YYQCXXX | D22: Construction | E22: Common of Project | F22: 701009 | G22: Project Safety Equipment, Architectural per drawing | H22: Direct Cost | I22: Materials | J22: Permanent Material | L22: 0 | M22: 0 | N22: 0
C23: YYQCXXX | D23: Construction | E23: Load & Sail | F23: 701010 | G23: Seafastenning material, Skidding Support, Rigging P/F | H23: Direct Cost | I23: Materials | J23: Temporary Material | L23: 0 | M23: 0 | N23: 0
C24: YYQCXXX | D24: Construction | E24: Structure Steel | F24: 701011 | G24: Steel ( Not include NSC ) | H24: Direct Cost | I24: Materials | J24: Permanent Material | L24: 0 | M24: 0 | N24: 0
C25: YYQCXXX | D25: Construction | E25: Structure Steel | F25: 701012 | G25: Structure Procurement | H25: Direct Cost | I25: Materials | J25: Permanent Material | L25: 0 | M25: 0 | N25: 0
C26: YYQCXXX | D26: Construction | E26: Structure Steel | F26: 701013 | G26: Electrode for Structure | H26: Direct Cost | I26: Consumables | J26: Welding Electrode | L26: 0 | M26: 0 | N26: 0
C27: YYQCXXX | D27: Construction | E27: Blast & Paint | F27: 701014 | G27: Painting Material | H27: Direct Cost | I27: Consumables | J27: Painting Material | L27: 0 | M27: 0 | N27: 0
C28: YYQCXXX | D28: Construction | E28: Piping | F28: 701015 | G28: Piping Procurement | H28: Direct Cost | I28: Materials | J28: Permanent Material | L28: 0 | M28: 0 | N28: 0
C29: YYQCXXX | D29: Construction | E29: Electrical | F29: 701016 | G29: Electrical Procurement | H29: Direct Cost | I29: Materials | J29: Permanent Material | L29: 0 | M29: 0 | N29: 0
C30: YYQCXXX | D30: Construction | E30: Load & Sail | F30: 701017 | G30: Packing Material & Pre rigging ( Tenchnical ) | H30: Direct Cost | I30: Consumables | J30: General Consumable | L30: 0 | M30: 0 | N30: 0
C31: YYQCXXX | D31: Construction | E31: Structure Steel | F31: 701018 | G31: Other Consumable for Structure | H31: Direct Cost | I31: Consumables | J31: General Consumable | L31: 0 | M31: 0 | N31: 0
... C33: YYQCXXX | D33: Construction | E33: Instrument | F33: 701020 | G33: Instrument Procurement | H33: Direct Cost | I33: Materials | J33: Permanent Material | L33: 0 | M33: 0 | N33: 0
C34: YYQCXXX | D34: Construction | E34: Common of Project | F34: 701021 | G34: Fuel & Gasoline | H34: Direct Cost | I34: Consumables | J34: Fuel & Gasoline | K34: X | L34: 150000 | M34: 0 | N34: 0
C35: YYQCXXX | D35: Construction | E35: Common of Project | F35: 701022 | G35: Spare part | H35: Direct Cost | I35: Equipment and Tools | J35: General Tool | L35: 0 | M35: 0 | N35: 0
C36: YYQCXXX | D36: Construction | E36: Common of Project | F36: 701023 | G36: Loose tool Safety | H36: Direct Cost | I36: Consumables | J36: Safety and PPE | L36: 0 | M36: 0 | N36: 0
C37: YYQCXXX | D37: Construction | E37: Blast & Paint | F37: 701024 | G37: Grinding & Cutting for Structure | H37: Direct Cost | I37: Equipment and Tools | J37: General Tool | L37: 0 | M37: 0 | N37: 0
C38: YYQCXXX | D38: Construction | E38: Structure Steel | F38: 701025 | G38: Machining, Bending , Gavanizing, Drilling & Tap for Structure | H38: Direct Cost | I38: Service Work & Supply | J38: Machining, Bending , Gavanizing, Drilling & Tap and PWHT | L38: 0 | M38: 0 | N38: 0
C39: YYQCXXX | D39: Construction | E39: Common of Project | F39: 701026 | G39: Welding Cable and Other Accessory | H39: Direct Cost | I39: Equipment and Tools | J39: General Tool | L39: 0 | M39: 0 | N39: 0
C40: YYQCXXX | D40: Construction | E40: Load & Sail | F40: 701027 | G40: Loose tool - Technical | H40: Direct Cost | I40: Equipment and Tools | J40: General Tool | L40: 0 | M40: 0 | N40: 0
C41: YYQCXXX | D41: Construction | E41: Structure Steel | F41: 701028 | G41: Structure Consumable | H41: Direct Cost | I41: Consumables | J41: General Consumable | L41: 0 | M41: 0 | N41: 0
C42: YYQCXXX | D42: Construction | E42: Blast & Paint | F42: 701029 | G42: Other Consumable for Blast & Paint | H42: Direct Cost | I42: Consumables | J42: General Consumable | L42: 0 | M42: 0 | N42: 0
C43: YYQCXXX | D43: Construction | E43: Piping | F43: 701030 | G43: Process Testing for Process Piping & Mechanical | H43: Direct Cost | I43: Service Work & Supply | J43: General Service | L43: 0 | M43: 0 | N43: 0
C44: YYQCXXX | D44: Construction | E44: Common of Project | F44: 701031 | G44: Factory Instrument Calibration | H44: Direct Cost | I44: Equipment and Tools | J44: General Tool | L44: 0 | M44: 0 | N44: 0
C45: YYQCXXX | D45: Construction | E45: Common of Project | F45: 701032 | G45: Mechanical Procurement ( for Direct to the Project) | H45: Direct Cost | I45: Materials | J45: Permanent Material | L45: 0 | M45: 0 | N45: 0
C46: YYQCXXX | D46: Construction | E46: Common of Project | F46: 701034 | G46: Scaffolding Material & Maintenance Cost | H46: Direct Cost | I46: Equipment and Tools | J46: General Tool | L46: 0 | M46: 0 | N46: 0
... C50: YYQCXXX | D50: Construction | E50: Common of Project | F50: 701119 | G50: Final Document | H50: Direct Cost | I50: Expense | J50: General Expense | L50: 0 | M50: 0 | N50: 0
C51: YYQCXXX | D51: Construction | E51: Common of Project | F51: 701120 | G51: Third Party Inspection | H51: Direct Cost | I51: Expense | J51: General Expense | K51: X | L51: 1 | M51: 1 | N51: 1
C52: YYQCXXX | D52: Construction | E52: Common of Project | F52: 701121 | G52: Third party Expediting | H52: Direct Cost | I52: Expense | J52: General Expense | L52: 0 | M52: 0 | N52: 0
C53: YYQCXXX | D53: Construction | E53: Common of Project | F53: 701122 | G53: Work order cost related to Material/Equipment | H53: Direct Cost | I53: Service Work & Supply | J53: General Service | L53: 0 | M53: 0 | N53: 0
C54: YYQCXXX | D54: Construction | E54: Common of Project | F54: 701123 | G54: Transportation cost between vendor premise and Thai port | H54: Direct Cost | I54: Expense | J54: General Expense | L54: 0 | M54: 0 | N54: 0
C55: YYQCXXX | D55: Construction | E55: Structure Steel | F55: 701127 | G55: Loose Tool - Structure | H55: Direct Cost | I55: Equipment and Tools | J55: General Tool | L55: 0 | M55: 0 | N55: 0
C56: YYQCXXX | D56: Construction | E56: Piping | F56: 701213 | G56: Electrode for Piping & Mechanical | H56: Direct Cost | I56: Consumables | J56: Welding Electrode | L56: 0 | M56: 0 | N56: 0
C57: YYQCXXX | D57: Construction | E57: Mechanical | F57: 701214 | G57: Electrode for Vessel | H57: Direct Cost | I57: Consumables | J57: Welding Electrode | L57: 0 | M57: 0 | N57: 0
C58: YYQCXXX | D58: Construction | E58: Electrical | F58: 701215 | G58: Electrode for E&I | H58: Direct Cost | I58: Consumables | J58: Welding Electrode | L58: 0 | M58: 0 | N58: 0
C59: YYQCXXX | D59: Construction | E59: Process | F59: 701227 | G59: Loose Tool - Process | H59: Direct Cost | I59: Equipment and Tools | J59: General Tool | L59: 0 | M59: 0 | N59: 0
C60: YYQCXXX | D60: Construction | E60: Electrical | F60: 701327 | G60: Loose Tools - E/I | H60: Direct Cost | I60: Equipment and Tools | J60: General Tool | L60: 0 | M60: 0 | N60: 0
C61: YYQCXXX | D61: Construction | E61: Common of Project | F61: 701427 | G61: Loose Tools Inspection (NDE) | H61: Direct Cost | I61: Equipment and Tools | J61: For WPQT, WQT, Inspection & NDE2 | L61: 0 | M61: 0 | N61: 0
C62: YYQCXXX | D62: Construction | E62: Common of Project | F62: 701527 | G62: Loose Tool Matecon | H62: Direct Cost | I62: Equipment and Tools | J62: General Tool | L62: 0 | M62: 0 | N62: 0
C63: YYQCXXX | D63: Construction | E63: Common of Project | F63: 701627 | G63: Loos tool Shop design | H63: Direct Cost | I63: Equipment and Tools | J63: General Tool | L63: 0 | M63: 0 | N63: 0
... C73: YYQCXXX | D73: Construction | E73: Common of Project | F73: 703016 | G73: Japanese Engineer expenses | H73: Direct Cost | I73: Expense | J73: Staff Expense | L73: 0 | M73: 0 | N73: 0
C74: YYQCXXX | D74: Construction | E74: Common of Project | F74: 703017 | G74: Apartment Rental & Service | H74: Direct Cost | I74: Expense | J74: Staff Expense | K74: X | L74: 0 | M74: 235620 | N74: 378907
C75: YYQCXXX | D75: Construction | E75: Common of Project | F75: 703018 | G75: Postage and Courier charges | H75: Direct Cost | I75: Expense | J75: Staff Expense | L75: 0 | M75: 0 | N75: 0
C76: YYQCXXX | D76: Construction | E76: Common of Project | F76: 703019 | G76: Expenses - Others | H76: Direct Cost | I76: Expense | J76: Staff Expense | K76: X | L76: 0 | M76: 0 | N76: 4605216
C77: YYQCXXX | D77: Construction | E77: Common of Project | F77: 703210 | G77: Maintenance Building | H77: Direct Cost | I77: Expense | J77: General Expense | L77: 0 | M77: 0 | N77: 0
C78: YYQCXXX | D78: Construction | E78: Common of Project | F78: 703211 | G78: Maintenance Equipment | H78: Direct Cost | I78: Expense | J78: General Expense | L78: 0 | M78: 0 | N78: 0
C79: YYQCXXX | D79: Construction | E79: Common of Project | F79: 703212 | G79: Maintenance Tool | H79: Direct Cost | I79: Expense | J79: General Expense | L79: 0 | M79: 0 | N79: 0
C80: YYQCXXX | D80: Construction | E80: Common of Project | F80: 703213 | G80: Maintenance Car | H80: Direct Cost | I80: Expense | J80: General Expense | L80: 0 | M80: 0 | N80: 0
C81: YYQCXXX | D81: Construction | E81: Common of Project | F81: 703214 | G81: Maintenance Yard Facility | H81: Direct Cost | I81: Expense | J81: General Expense | L81: 0 | M81: 0 | N81: 0
C82: YYQCXXX | D82: Construction | E82: Blast & Paint | F82: 703215 | G82: Maintenance Blast Painting | H82: Direct Cost | I82: Expense | J82: General Expense | L82: 0 | M82: 0 | N82: 0
C83: YYQCXXX | D83: Construction | E83: Common of Project | F83: 703216 | G83: Maintenance Yard Facility and Other Facility (Include Blast Painting and for all production yard facility) | H83: Direct Cost | I83: Expense | J83: General Expense | L83: 0 | M83: 0 | N83: 0
C84: YYQCXXX | D84: Construction | E84: Common of Project | F84: 703217 | G84: Maintenance Equipment for Engineering | H84: Direct Cost | I84: Expense | J84: General Expense | L84: 0 | M84: 0 | N84: 0
C85: YYQCXXX | D85: Construction | E85: Common of Project | F85: 703219 | G85: Maintenance Others | H85: Direct Cost | I85: Expense | J85: General Expense | L85: 0 | M85: 0 | N85: 0
C86: YYQCXXX | D86: Construction | E86: Common of Project | F86: 703220 | G86: WPQT WQT Production Test & SSCC Test | H86: Direct Cost | I86: Service Work & Supply | J86: For WPQT, WQT, Inspection & NDE3 | L86: 0 | M86: 0 | N86: 0
C87: YYQCXXX | D87: Construction | E87: Structure Steel | F87: 703221 | G87: Manpower Supply for Structure Welder | H87: Direct Cost | I87: MPS Labor | J87: MPS Labor Direct | L87: 0 | M87: 0 | N87: 0
C88: YYQCXXX | D88: Construction | E88: Blast & Paint | F88: 703222 | G88: Manpower Supply for Blast & Paint | H88: Direct Cost | I88: MPS Labor | J88: MPS Labor Direct | L88: 0 | M88: 0 | N88: 0
... C93: YYQCXXX | D93: Construction | E93: Structure Steel | F93: 703227 | G93: Manpower Supply for Structure Fitter & Other | H93: Direct Cost | I93: MPS Labor | J93: MPS Labor Direct | L93: 0 | M93: 0 | N93: 0
C94: YYQCXXX | D94: Construction | E94: Piping | F94: 703228 | G94: Lump Sum Sub-Contract for Piping & Mechanical | H94: Direct Cost | I94: LS Subcontract | J94: LS Subcontract | K94: X | L94: 4198908.4 | M94: 4198908 | N94: 4166590.4
C95: YYQCXXX | D95: Construction | E95: Load & Sail | F95: 703229 | G95: Lump Sum for Dredging, Load Out for Technical | H95: Direct Cost | I95: LS Subcontract | J95: LS Subcontract | L95: 0 | M95: 0 | N95: 0
C96: YYQCXXX | D96: Construction | E96: Electrical | F96: 703230 | G96: Lump Sum Sub-Contract for E&I | H96: Direct Cost | I96: LS Subcontract | J96: LS Subcontract | K96: X | L96: 15621938 | M96: 17103639 | N96: 16077467
C97: YYQCXXX | D97: Construction | E97: Common of Project | F97: 703231 | G97: Manpower Supply for Factory Service / Maintenance | H97: Direct Cost | I97: MPS Labor | J97: MPS Labor Indirect | L97: 0 | M97: 0 | N97: 0
C98: YYQCXXX | D98: Construction | E98: Structure Steel | F98: 703232 | G98: Lump Sum Sub-Contract for Structure | H98: Direct Cost | I98: LS Subcontract | J98: LS Subcontract | L98: 0 | M98: 0 | N98: 0
C99: YYQCXXX | D99: Construction | E99: Load & Sail | F99: 703233 | G99: Transportation (Barge&Tug included fuel) | H99: Direct Cost | I99: Service Work & Supply | J99: Transportation Rental | L99: 0 | M99: 0 | N99: 0
C100: YYQCXXX | D100: Construction | E100: Common of Project | F100: 703234 | G100: Rental Truck , Trailer, Forklift, JCB | H100: Direct Cost | I100: Service Work & Supply | J100: Transportation Rental | K100: X | L100: 301000 | M100: 301000 | N100: 50000
C101: YYQCXXX | D101: Construction | E101: Common of Project | F101: 703235 | G101: Rental Crane | H101: Direct Cost | I101: Service Work & Supply | J101: Transportation Rental | L101: 0 | M101: 0 | N101: 0
C102: YYQCXXX | D102: Construction | E102: Load & Sail | F102: 703236 | G102: Other Heavy equipment (Heavy Crane ) | H102: Direct Cost | I102: Equipment and Tools | J102: General Tool | L102: 0 | M102: 0 | N102: 0
C103: YYQCXXX | D103: Construction | E103: Common of Project | F103: 703237 | G103: Forwarding expenses (included duty examption fee, | H103: Direct Cost | I103: Expense | J103: General Expense | L103: 0 | M103: 0 | N103: 0
C104: YYQCXXX | D104: Construction | E104: Piping | F104: 703238 | G104: Piping Consumable except electrode incl. Gas | H104: Direct Cost | I104: Consumables | J104: General Consumable | L104: 0 | M104: 0 | N104: 0
C105: YYQCXXX | D105: Construction | E105: Common of Project | F105: 703239 | G105: Preservation and Storage for Material Control | H105: Direct Cost | I105: Consumables | J105: General Consumable | L105: 0 | M105: 0 | N105: 0
C106: YYQCXXX | D106: Construction | E106: Electrical | F106: 703240 | G106: Other Consumable for E&I | H106: Direct Cost | I106: Consumables | J106: General Consumable | L106: 0 | M106: 0 | N106: 0
C107: YYQCXXX | D107: Construction | E107: Common of Project | F107: 703241 | G107: Manpower Supply for Engineer | H107: Direct Cost | I107: MPS Labor | J107: MPS Labor Indirect | L107: 0 | M107: 0 | N107: 0
C108: YYQCXXX | D108: Construction | E108: Architechture | F108: 703241 | G108: Manpower Supply for Engineer | H108: Direct Cost | I108: MPS Labor | J108: MPS Labor Indirect | L108: 0 | M108: 0 | N108: 0
C109: YYQCXXX | D109: Construction | E109: Civil | F109: 703241 | G109: Manpower Supply for Engineer | H109: Direct Cost | I109: MPS Labor | J109: MPS Labor Indirect | L109: 0 | M109: 0 | N109: 0
C110: YYQCXXX | D110: Construction | E110: CSA | F110: 703241 | G110: Manpower Supply for Engineer | H110: Direct Cost | I110: MPS Labor | J110: MPS Labor Indirect | L110: 0 | M110: 0 | N110: 0
C111: YYQCXXX | D111: Construction | E111: Structure Steel | F111: 703241 | G111: Manpower Supply for Engineer | H111: Direct Cost | I111: MPS Labor | J111: MPS Labor Indirect | L111: 0 | M111: 0 | N111: 0
C112: YYQCXXX | D112: Construction | E112: Piping | F112: 703241 | G112: Manpower Supply for Engineer | H112: Direct Cost | I112: MPS Labor | J112: MPS Labor Indirect | L112: 0 | M112: 0 | N112: 0
... C117: YYQCXXX | D117: Construction | E117: Common of Project | F117: 703242 | G117: Manpower Supply for Material Control & Store | H117: Direct Cost | I117: MPS Labor | J117: MPS Labor Indirect | L117: 0 | M117: 0 | N117: 0
C118: YYQCXXX | D118: Construction | E118: Common of Project | F118: 703243 | G118: M/P for service to Company | H118: Direct Cost | I118: MPS Labor | J118: MPS Labor Indirect | K118: X | L118: 0 | M118: 846000 | N118: 542931.25
C119: YYQCXXX | D119: Construction | E119: Common of Project | F119: 703244 | G119: PFP & Actuator | H119: Direct Cost | I119: Service Work & Supply | J119: General Service | L119: 0 | M119: 0 | N119: 0
C120: YYQCXXX | D120: Construction | E120: Piping | F120: 703245 | G120: Manpower Supply for Piping & Mechanical | H120: Direct Cost | I120: MPS Labor | J120: MPS Labor Direct | L120: 0 | M120: 0 | N120: 0
C121: YYQCXXX | D121: Construction | E121: Common of Project | F121: 703246 | G121: Manpower Supply for Vessel | H121: Direct Cost | I121: MPS Labor | J121: MPS Labor Direct | L121: 0 | M121: 0 | N121: 0
C122: YYQCXXX | D122: Construction | E122: Electrical | F122: 703247 | G122: Manpower Supply for E&I | H122: Direct Cost | I122: MPS Labor | J122: MPS Labor Direct | L122: 0 | M122: 0 | N122: 0
C123: YYQCXXX | D123: Construction | E123: Common of Project | F123: 703248 | G123: Manpower Supply for HSE | H123: Direct Cost | I123: MPS Labor | J123: MPS Labor Indirect | K123: X | L123: 0 | M123: 915702.67 | N123: 0
C124: YYQCXXX | D124: Construction | E124: Blast & Paint | F124: 703249 | G124: Lump Sum Sub-Contract for Blast & Paint | H124: Direct Cost | I124: LS Subcontract | J124: LS Subcontract | L124: 0 | M124: 0 | N124: 0
C125: YYQCXXX | D125: Construction | E125: Mechanical | F125: 703250 | G125: Machining, Bending , Gavanizing, Drilling & Tap and PWHT for Vessel | H125: Direct Cost | I125: Service Work & Supply | J125: Equipment Rental | L125: 0 | M125: 0 | N125: 0
C126: YYQCXXX | D126: Construction | E126: Common of Project | F126: 703251 | G126: Base Salary + Overtime for Expat Agency | H126: Direct Cost | I126: Expense | J126: Staff Expense | L126: 0 | M126: 0 | N126: 0
C127: YYQCXXX | D127: Construction | E127: Common of Project | F127: 703252 | G127: Allowance for Expat Agency | H127: Direct Cost | I127: Expense | J127: Staff Expense | L127: 0 | M127: 0 | N127: 0
C128: YYQCXXX | D128: Construction | E128: Common of Project | F128: 703253 | G128: Travelling Expense for Expat Agency | H128: Direct Cost | I128: Expense | J128: Staff Expense | L128: 0 | M128: 0 | N128: 0
C129: YYQCXXX | D129: Construction | E129: Common of Project | F129: 703254 | G129: Room Rental for Expat Agency | H129: Direct Cost | I129: Expense | J129: Staff Expense | L129: 0 | M129: 0 | N129: 0
...

Sheet Validate_Empty
C8: TRUE | D8: TRUE | E8: TRUE | F8: TRUE | G8: TRUE | H8: TRUE | I8: FALSE | J8: FALSE | K8: FALSE | L8: FALSE | M8: FALSE | N8: FALSE
C9: C1 | D9: C2 | E9: C3 | F9: C4 | G9: C5 | H9: C6 | I9: C7 | J9: C8 | K9: C9 | L9: C10 | M9: C11 | N9: C12
C10: {=IFERROR(IF(OR('Raw Data'!C10="",LEN(TRIM('Raw Data'!C10))=0),_xlfn.REGEXEXTRACT(CELL("address",'Raw Data'!C10),"\$([A-Z]+)\$[0-9]+"),""),"")} | D10: {=IFERROR(IF(OR('Raw Data'!D10="",LEN(TRIM('Raw Data'!D10))=0),_xlfn.REGEXEXTRACT(CELL("address",'Raw Data'!D10),"\$([A-Z]+)\$[0-9]+"),""),"")} | E10: {=IFERROR(IF(OR('Raw Data'!E10="",LEN(TRIM('Raw Data'!E10))=0),_xlfn.REGEXEXTRACT(CELL("address",'Raw Data'!E10),"\$([A-Z]+)\$[0-9]+"),""),"")} | F10: {=IFERROR(IF(OR('Raw Data'!F10="",LEN(TRIM('Raw Data'!F10))=0),_xlfn.REGEXEXTRACT(CELL("address",'Raw Data'!F10),"\$([A-Z]+)\$[0-9]+"),""),"")} | G10: {=IFERROR(IF(OR('Raw Data'!G10="",LEN(TRIM('Raw Data'!G10))=0),_xlfn.REGEXEXTRACT(CELL("address",'Raw Data'!G10),"\$([A-Z]+)\$[0-9]+"),""),"")} | H10: {=IFERROR(IF(OR('Raw Data'!H10="",LEN(TRIM('Raw Data'!H10))=0),_xlfn.REGEXEXTRACT(CELL("address",'Raw Data'!H10),"\$([A-Z]+)\$[0-9]+"),""),"")}
C11: {=IFERROR(IF(OR('Raw Data'!C11="",LEN(TRIM('Raw Data'!C11))=0),_xlfn.REGEXEXTRACT(CELL("address",'Raw Data'!C11),"\$([A-Z]+)\$[0-9]+"),""),"")} | D11: {=IFERROR(IF(OR('Raw Data'!D11="",LEN(TRIM('Raw Data'!D11))=0),_xlfn.REGEXEXTRACT(CELL("address",'Raw Data'!D11),"\$([A-Z]+)\$[0-9]+"),""),"")} | E11: {=IFERROR(IF(OR('Raw Data'!E11="",LEN(TRIM('Raw Data'!E11))=0),_xlfn.REGEXEXTRACT(CELL("address",'Raw Data'!E11),"\$([A-Z]+)\$[0-9]+"),""),"")} | F11: {=IFERROR(IF(OR('Raw Data'!F11="",LEN(TRIM('Raw Data'!F11))=0),_xlfn.REGEXEXTRACT(CELL("address",'Raw Data'!F11),"\$([A-Z]+)\$[0-9]+"),""),"")} | G11: {=IFERROR(IF(OR('Raw Data'!G11="",LEN(TRIM('Raw Data'!G11))=0),_xlfn.REGEXEXTRACT(CELL("address",'Raw Data'!G11),"\$([A-Z]+)\$[0-9]+"),""),"")} | H11: {=IFERROR(IF(OR('Raw Data'!H11="",LEN(TRIM('Raw Data'!H11))=0),_xlfn.REGEXEXTRACT(CELL("address",'Raw Data'!H11),"\$([A-Z]+)\$[0-9]+"),""),"")}
C12: {=IFERROR(IF(OR('Raw Data'!C12="",LEN(TRIM('Raw Data'!C12))=0),_xlfn.REGEXEXTRACT(CELL("address",'Raw Data'!C12),"\$([A-Z]+)\$[0-9]+"),""),"")} | D12: {=IFERROR(IF(OR('Raw Data'!D12="",LEN(TRIM('Raw Data'!D12))=0),_xlfn.REGEXEXTRACT(CELL("address",'Raw Data'!D12),"\$([A-Z]+)\$[0-9]+"),""),"")} | E12: {=IFERROR(IF(OR('Raw Data'!E12="",LEN(TRIM('Raw Data'!E12))=0),_xlfn.REGEXEXTRACT(CELL("address",'Raw Data'!E12),"\$([A-Z]+)\$[0-9]+"),""),"")} | F12: {=IFERROR(IF(OR('Raw Data'!F12="",LEN(TRIM('Raw Data'!F12))=0),_xlfn.REGEXEXTRACT(CELL("address",'Raw Data'!F12),"\$([A-Z]+)\$[0-9]+"),""),"")} | G12: {=IFERROR(IF(OR('Raw Data'!G12="",LEN(TRIM('Raw Data'!G12))=0),_xlfn.REGEXEXTRACT(CELL("address",'Raw Data'!G12),"\$([A-Z]+)\$[0-9]+"),""),"")} | H12: {=IFERROR(IF(OR('Raw Data'!H12="",LEN(TRIM('Raw Data'!H12))=0),_xlfn.REGEXEXTRACT(CELL("address",'Raw Data'!H12),"\$([A-Z]+)\$[0-9]+"),""),"")}
C13: {=IFERROR(IF(OR('Raw Data'!C13="",LEN(TRIM('Raw Data'!C13))=0),_xlfn.REGEXEXTRACT(CELL("address",'Raw Data'!C13),"\$([A-Z]+)\$[0-9]+"),""),"")} | D13: {=IFERROR(IF(OR('Raw Data'!D13="",LEN(TRIM('Raw Data'!D13))=0),_xlfn.REGEXEXTRACT(CELL("address",'Raw Data'!D13),"\$([A-Z]+)\$[0-9]+"),""),"")} | E13: {=IFERROR(IF(OR('Raw Data'!E13="",LEN(TRIM('Raw Data'!E13))=0),_xlfn.REGEXEXTRACT(CELL("address",'Raw Data'!E13),"\$([A-Z]+)\$[0-9]+"),""),"")} | F13: {=IFERROR(IF(OR('Raw Data'!F13="",LEN(TRIM('Raw Data'!F13))=0),_xlfn.REGEXEXTRACT(CELL("address",'Raw Data'!F13),"\$([A-Z]+)\$[0-9]+"),""),"")} | G13: {=IFERROR(IF(OR('Raw Data'!G13="",LEN(TRIM('Raw Data'!G13))=0),_xlfn.REGEXEXTRACT(CELL("address",'Raw Data'!G13),"\$([A-Z]+)\$[0-9]+"),""),"")} | H13: {=IFERROR(IF(OR('Raw Data'!H13="",LEN(TRIM('Raw Data'!H13))=0),_xlfn.REGEXEXTRACT(CELL("address",'Raw Data'!H13),"\$([A-Z]+)\$[0-9]+"),""),"")}
C14: {=IFERROR(IF(OR('Raw Data'!C14="",LEN(TRIM('Raw Data'!C14))=0),_xlfn.REGEXEXTRACT(CELL("address",'Raw Data'!C14),"\$([A-Z]+)\$[0-9]+"),""),"")} | D14: {=IFERROR(IF(OR('Raw Data'!D14="",LEN(TRIM('Raw Data'!D14))=0),_xlfn.REGEXEXTRACT(CELL("address",'Raw Data'!D14),"\$([A-Z]+)\$[0-9]+"),""),"")} | E14: {=IFERROR(IF(OR('Raw Data'!E14="",LEN(TRIM('Raw Data'!E14))=0),_xlfn.REGEXEXTRACT(CELL("address",'Raw Data'!E14),"\$([A-Z]+)\$[0-9]+"),""),"")} | F14: {=IFERROR(IF(OR('Raw Data'!F14="",LEN(TRIM('Raw Data'!F14))=0),_xlfn.REGEXEXTRACT(CELL("address",'Raw Data'!F14),"\$([A-Z]+)\$[0-9]+"),""),"")} | G14: {=IFERROR(IF(OR('Raw Data'!G14="",LEN(TRIM('Raw Data'!G14))=0),_xlfn.REGEXEXTRACT(CELL("address",'Raw Data'!G14),"\$([A-Z]+)\$[0-9]+"),""),"")} | H14: {=IFERROR(IF(OR('Raw Data'!H14="",LEN(TRIM('Raw Data'!H14))=0),_xlfn.REGEXEXTRACT(CELL("address",'Raw Data'!H14),"\$([A-Z]+)\$[0-9]+"),""),"")}
C15: {=IFERROR(IF(OR('Raw Data'!C15="",LEN(TRIM('Raw Data'!C15))=0),_xlfn.REGEXEXTRACT(CELL("address",'Raw Data'!C15),"\$([A-Z]+)\$[0-9]+"),""),"")} | D15: {=IFERROR(IF(OR('Raw Data'!D15="",LEN(TRIM('Raw Data'!D15))=0),_xlfn.REGEXEXTRACT(CELL("address",'Raw Data'!D15),"\$([A-Z]+)\$[0-9]+"),""),"")} | E15: {=IFERROR(IF(OR('Raw Data'!E15="",LEN(TRIM('Raw Data'!E15))=0),_xlfn.REGEXEXTRACT(CELL("address",'Raw Data'!E15),"\$([A-Z]+)\$[0-9]+"),""),"")} | F15: {=IFERROR(IF(OR('Raw Data'!F15="",LEN(TRIM('Raw Data'!F15))=0),_xlfn.REGEXEXTRACT(CELL("address",'Raw Data'!F15),"\$([A-Z]+)\$[0-9]+"),""),"")} | G15: {=IFERROR(IF(OR('Raw Data'!G15="",LEN(TRIM('Raw Data'!G15))=0),_xlfn.REGEXEXTRACT(CELL("address",'Raw Data'!G15),"\$([A-Z]+)\$[0-9]+"),""),"")} | H15: {=IFERROR(IF(OR('Raw Data'!H15="",LEN(TRIM('Raw Data'!H15))=0),_xlfn.REGEXEXTRACT(CELL("address",'Raw Data'!H15),"\$([A-Z]+)\$[0-9]+"),""),"")}
C16: {=IFERROR(IF(OR('Raw Data'!C16="",LEN(TRIM('Raw Data'!C16))=0),_xlfn.REGEXEXTRACT(CELL("address",'Raw Data'!C16),"\$([A-Z]+)\$[0-9]+"),""),"")} | D16: {=IFERROR(IF(OR('Raw Data'!D16="",LEN(TRIM('Raw Data'!D16))=0),_xlfn.REGEXEXTRACT(CELL("address",'Raw Data'!D16),"\$([A-Z]+)\$[0-9]+"),""),"")} | E16: {=IFERROR(IF(OR('Raw Data'!E16="",LEN(TRIM('Raw Data'!E16))=0),_xlfn.REGEXEXTRACT(CELL("address",'Raw Data'!E16),"\$([A-Z]+)\$[0-9]+"),""),"")} | F16: {=IFERROR(IF(OR('Raw Data'!F16="",LEN(TRIM('Raw Data'!F16))=0),_xlfn.REGEXEXTRACT(CELL("address",'Raw Data'!F16),"\$([A-Z]+)\$[0-9]+"),""),"")} | G16: {=IFERROR(IF(OR('Raw Data'!G16="",LEN(TRIM('Raw Data'!G16))=0),_xlfn.REGEXEXTRACT(CELL("address",'Raw Data'!G16),"\$([A-Z]+)\$[0-9]+"),""),"")} | H16: {=IFERROR(IF(OR('Raw Data'!H16="",LEN(TRIM('Raw Data'!H16))=0),_xlfn.REGEXEXTRACT(CELL("address",'Raw Data'!H16),"\$([A-Z]+)\$[0-9]+"),""),"")}
C17: {=IFERROR(IF(OR('Raw Data'!C17="",LEN(TRIM('Raw Data'!C17))=0),_xlfn.REGEXEXTRACT(CELL("address",'Raw Data'!C17),"\$([A-Z]+)\$[0-9]+"),""),"")} | D17: {=IFERROR(IF(OR('Raw Data'!D17="",LEN(TRIM('Raw Data'!D17))=0),_xlfn.REGEXEXTRACT(CELL("address",'Raw Data'!D17),"\$([A-Z]+)\$[0-9]+"),""),"")} | E17: {=IFERROR(IF(OR('Raw Data'!E17="",LEN(TRIM('Raw Data'!E17))=0),_xlfn.REGEXEXTRACT(CELL("address",'Raw Data'!E17),"\$([A-Z]+)\$[0-9]+"),""),"")} | F17: {=IFERROR(IF(OR('Raw Data'!F17="",LEN(TRIM('Raw Data'!F17))=0),_xlfn.REGEXEXTRACT(CELL("address",'Raw Data'!F17),"\$([A-Z]+)\$[0-9]+"),""),"")} | G17: {=IFERROR(IF(OR('Raw Data'!G17="",LEN(TRIM('Raw Data'!G17))=0),_xlfn.REGEXEXTRACT(CELL("address",'Raw Data'!G17),"\$([A-Z]+)\$[0-9]+"),""),"")} | H17: {=IFERROR(IF(OR('Raw Data'!H17="",LEN(TRIM('Raw Data'!H17))=0),_xlfn.REGEXEXTRACT(CELL("address",'Raw Data'!H17),"\$([A-Z]+)\$[0-9]+"),""),"")}
C18: {=IFERROR(IF(OR('Raw Data'!C18="",LEN(TRIM('Raw Data'!C18))=0),_xlfn.REGEXEXTRACT(CELL("address",'Raw Data'!C18),"\$([A-Z]+)\$[0-9]+"),""),"")} | D18: {=IFERROR(IF(OR('Raw Data'!D18="",LEN(TRIM('Raw Data'!D18))=0),_xlfn.REGEXEXTRACT(CELL("address",'Raw Data'!D18),"\$([A-Z]+)\$[0-9]+"),""),"")} | E18: {=IFERROR(IF(OR('Raw Data'!E18="",LEN(TRIM('Raw Data'!E18))=0),_xlfn.REGEXEXTRACT(CELL("address",'Raw Data'!E18),"\$([A-Z]+)\$[0-9]+"),""),"")} | F18: {=IFERROR(IF(OR('Raw Data'!F18="",LEN(TRIM('Raw Data'!F18))=0),_xlfn.REGEXEXTRACT(CELL("address",'Raw Data'!F18),"\$([A-Z]+)\$[0-9]+"),""),"")} | G18: {=IFERROR(IF(OR('Raw Data'!G18="",LEN(TRIM('Raw Data'!G18))=0),_xlfn.REGEXEXTRACT(CELL("address",'Raw Data'!G18),"\$([A-Z]+)\$[0-9]+"),""),"")} | H18: {=IFERROR(IF(OR('Raw Data'!H18="",LEN(TRIM('Raw Data'!H18))=0),_xlfn.REGEXEXTRACT(CELL("address",'Raw Data'!H18),"\$([A-Z]+)\$[0-9]+"),""),"")}
C19: {=IFERROR(IF(OR('Raw Data'!C19="",LEN(TRIM('Raw Data'!C19))=0),_xlfn.REGEXEXTRACT(CELL("address",'Raw Data'!C19),"\$([A-Z]+)\$[0-9]+"),""),"")} | D19: {=IFERROR(IF(OR('Raw Data'!D19="",LEN(TRIM('Raw Data'!D19))=0),_xlfn.REGEXEXTRACT(CELL("address",'Raw Data'!D19),"\$([A-Z]+)\$[0-9]+"),""),"")} | E19: {=IFERROR(IF(OR('Raw Data'!E19="",LEN(TRIM('Raw Data'!E19))=0),_xlfn.REGEXEXTRACT(CELL("address",'Raw Data'!E19),"\$([A-Z]+)\$[0-9]+"),""),"")} | F19: {=IFERROR(IF(OR('Raw Data'!F19="",LEN(TRIM('Raw Data'!F19))=0),_xlfn.REGEXEXTRACT(CELL("address",'Raw Data'!F19),"\$([A-Z]+)\$[0-9]+"),""),"")} | G19: {=IFERROR(IF(OR('Raw Data'!G19="",LEN(TRIM('Raw Data'!G19))=0),_xlfn.REGEXEXTRACT(CELL("address",'Raw Data'!G19),"\$([A-Z]+)\$[0-9]+"),""),"")} | H19: {=IFERROR(IF(OR('Raw Data'!H19="",LEN(TRIM('Raw Data'!H19))=0),_xlfn.REGEXEXTRACT(CELL("address",'Raw Data'!H19),"\$([A-Z]+)\$[0-9]+"),""),"")}
C20: {=IFERROR(IF(OR('Raw Data'!C20="",LEN(TRIM('Raw Data'!C20))=0),_xlfn.REGEXEXTRACT(CELL("address",'Raw Data'!C20),"\$([A-Z]+)\$[0-9]+"),""),"")} | D20: {=IFERROR(IF(OR('Raw Data'!D20="",LEN(TRIM('Raw Data'!D20))=0),_xlfn.REGEXEXTRACT(CELL("address",'Raw Data'!D20),"\$([A-Z]+)\$[0-9]+"),""),"")} | E20: {=IFERROR(IF(OR('Raw Data'!E20="",LEN(TRIM('Raw Data'!E20))=0),_xlfn.REGEXEXTRACT(CELL("address",'Raw Data'!E20),"\$([A-Z]+)\$[0-9]+"),""),"")} | F20: {=IFERROR(IF(OR('Raw Data'!F20="",LEN(TRIM('Raw Data'!F20))=0),_xlfn.REGEXEXTRACT(CELL("address",'Raw Data'!F20),"\$([A-Z]+)\$[0-9]+"),""),"")} | G20: {=IFERROR(IF(OR('Raw Data'!G20="",LEN(TRIM('Raw Data'!G20))=0),_xlfn.REGEXEXTRACT(CELL("address",'Raw Data'!G20),"\$([A-Z]+)\$[0-9]+"),""),"")} | H20: {=IFERROR(IF(OR('Raw Data'!H20="",LEN(TRIM('Raw Data'!H20))=0),_xlfn.REGEXEXTRACT(CELL("address",'Raw Data'!H20),"\$([A-Z]+)\$[0-9]+"),""),"")}
C21: {=IFERROR(IF(OR('Raw Data'!C21="",LEN(TRIM('Raw Data'!C21))=0),_xlfn.REGEXEXTRACT(CELL("address",'Raw Data'!C21),"\$([A-Z]+)\$[0-9]+"),""),"")} | D21: {=IFERROR(IF(OR('Raw Data'!D21="",LEN(TRIM('Raw Data'!D21))=0),_xlfn.REGEXEXTRACT(CELL("address",'Raw Data'!D21),"\$([A-Z]+)\$[0-9]+"),""),"")} | E21: {=IFERROR(IF(OR('Raw Data'!E21="",LEN(TRIM('Raw Data'!E21))=0),_xlfn.REGEXEXTRACT(CELL("address",'Raw Data'!E21),"\$([A-Z]+)\$[0-9]+"),""),"")} | F21: {=IFERROR(IF(OR('Raw Data'!F21="",LEN(TRIM('Raw Data'!F21))=0),_xlfn.REGEXEXTRACT(CELL("address",'Raw Data'!F21),"\$([A-Z]+)\$[0-9]+"),""),"")} | G21: {=IFERROR(IF(OR('Raw Data'!G21="",LEN(TRIM('Raw Data'!G21))=0),_xlfn.REGEXEXTRACT(CELL("address",'Raw Data'!G21),"\$([A-Z]+)\$[0-9]+"),""),"")} | H21: {=IFERROR(IF(OR('Raw Data'!H21="",LEN(TRIM('Raw Data'!H21))=0),_xlfn.REGEXEXTRACT(CELL("address",'Raw Data'!H21),"\$([A-Z]+)\$[0-9]+"),""),"")}
... C1259: {=IFERROR(IF(OR('Raw Data'!C1259="",LEN(TRIM('Raw Data'!C1259))=0),_xlfn.REGEXEXTRACT(CELL("address",'Raw Data'!C1259),"\$([A-Z]+)\$[0-9]+"),""),"")} | D1259: {=IFERROR(IF(OR('Raw Data'!D1259="",LEN(TRIM('Raw Data'!D1259))=0),_xlfn.REGEXEXTRACT(CELL("address",'Raw Data'!D1259),"\$([A-Z]+)\$[0-9]+"),""),"")} | E1259: {=IFERROR(IF(OR('Raw Data'!E1259="",LEN(TRIM('Raw Data'!E1259))=0),_xlfn.REGEXEXTRACT(CELL("address",'Raw Data'!E1259),"\$([A-Z]+)\$[0-9]+"),""),"")} | F1259: {=IFERROR(IF(OR('Raw Data'!F1259="",LEN(TRIM('Raw Data'!F1259))=0),_xlfn.REGEXEXTRACT(CELL("address",'Raw Data'!F1259),"\$([A-Z]+)\$[0-9]+"),""),"")} | G1259: {=IFERROR(IF(OR('Raw Data'!G1259="",LEN(TRIM('Raw Data'!G1259))=0),_xlfn.REGEXEXTRACT(CELL("address",'Raw Data'!G1259),"\$([A-Z]+)\$[0-9]+"),""),"")} | H1259: {=IFERROR(IF(OR('Raw Data'!H1259="",LEN(TRIM('Raw Data'!H1259))=0),_xlfn.REGEXEXTRACT(CELL("address",'Raw Data'!H1259),"\$([A-Z]+)\$[0-9]+"),""),"")}

Sheet Validate_Value
C8: NVARCHAR(20) | D8: NVARCHAR(255) | E8: NVARCHAR(255) | F8: NVARCHAR(50) | G8: NVARCHAR(255) | H8: NVARCHAR(255) | I8: NVARCHAR(255) | J8: NVARCHAR(255) | K8: NVARCHAR(10) | L8: DECIMAL(13,2) | M8: DECIMAL(13,2) | N8: DECIMAL(13,2)
C9: C1 | D9: C2 | E9: C3 | F9: C4 | G9: C5 | H9: C6 | I9: C7 | J9: C8 | K9: C9 | L9: C10 | M9: C11 | N9: C12
C10: {=IFERROR(IF(OR('Raw Data'!C10="",LEN(TRIM('Raw Data'!C10))=0),"",IF(AND(LEN('Raw Data'!C10) <= 20,LEN('Raw Data'!C10)> 0),"",_xlfn.REGEXEXTRACT(CELL("address",'Raw Data'!C10),"\$([A-Z]+)\$[0-9]+"))),_xlfn.REGEXEXTRACT(CELL("address",'Raw Data'!C10),"\$([A-Z]+)\$[0-9]+"))} | D10: {=IFERROR(IF(OR('Raw Data'!D10="",LEN(TRIM('Raw Data'!D10))=0),"",IF(AND(LEN('Raw Data'!D10) <= 255,LEN('Raw Data'!D10)> 0),"",_xlfn.REGEXEXTRACT(CELL("address",'Raw Data'!D10),"\$([A-Z]+)\$[0-9]+"))),_xlfn.REGEXEXTRACT(CELL("address",'Raw Data'!D10),"\$([A-Z]+)\$[0-9]+"))} | E10: {=IFERROR(IF(OR('Raw Data'!E10="",LEN(TRIM('Raw Data'!E10))=0),"",IF(AND(LEN('Raw Data'!E10) <= 255,LEN('Raw Data'!E10)> 0),"",_xlfn.REGEXEXTRACT(CELL("address",'Raw Data'!E10),"\$([A-Z]+)\$[0-9]+"))),_xlfn.REGEXEXTRACT(CELL("address",'Raw Data'!E10),"\$([A-Z]+)\$[0-9]+"))} | F10: {=IFERROR(IF(OR('Raw Data'!F10="",LEN(TRIM('Raw Data'!F10))=0),"",IF(AND(LEN('Raw Data'!F10) <= 50,LEN('Raw Data'!F10)> 0),"",_xlfn.REGEXEXTRACT(CELL("address",'Raw Data'!F10),"\$([A-Z]+)\$[0-9]+"))),_xlfn.REGEXEXTRACT(CELL("address",'Raw Data'!F10),"\$([A-Z]+)\$[0-9]+"))} | G10: {=IFERROR(IF(OR('Raw Data'!G10="",LEN(TRIM('Raw Data'!G10))=0),"",IF(AND(LEN('Raw Data'!G10) <= 255,LEN('Raw Data'!G10)> 0),"",_xlfn.REGEXEXTRACT(CELL("address",'Raw Data'!G10),"\$([A-Z]+)\$[0-9]+"))),_xlfn.REGEXEXTRACT(CELL("address",'Raw Data'!G10),"\$([A-Z]+)\$[0-9]+"))} | H10: {=IFERROR(IF(OR('Raw Data'!H10="",LEN(TRIM('Raw Data'!H10))=0),"",IF(AND(LEN('Raw Data'!H10) <= 255,LEN('Raw Data'!H10)> 0),"",_xlfn.REGEXEXTRACT(CELL("address",'Raw Data'!H10),"\$([A-Z]+)\$[0-9]+"))),_xlfn.REGEXEXTRACT(CELL("address",'Raw Data'!H10),"\$([A-Z]+)\$[0-9]+"))} | I10: {=IFERROR(IF(OR('Raw Data'!I10="",LEN(TRIM('Raw Data'!I10))=0),"",IF(AND(LEN('Raw Data'!I10) <= 255,LEN('Raw Data'!I10)> 0),"",_xlfn.REGEXEXTRACT(CELL("address",'Raw Data'!I10),"\$([A-Z]+)\$[0-9]+"))),_xlfn.REGEXEXTRACT(CELL("address",'Raw Data'!I10),"\$([A-Z]+)\$[0-9]+"))} | J10: {=IFERROR(IF(OR('Raw Data'!J10="",LEN(TRIM('Raw Data'!J10))=0),"",IF(AND(LEN('Raw Data'!J10) <= 255,LEN('Raw Data'!J10)> 0),"",_xlfn.REGEXEXTRACT(CELL("address",'Raw Data'!J10),"\$([A-Z]+)\$[0-9]+"))),_xlfn.REGEXEXTRACT(CELL("address",'Raw Data'!J10),"\$([A-Z]+)\$[0-9]+"))} | K10: {=IFERROR(IF(OR('Raw Data'!K10="",LEN(TRIM('Raw Data'!K10))=0),"",IF(AND(LEN('Raw Data'!K10) <= 10,LEN('Raw Data'!K10)> 0),"",_xlfn.REGEXEXTRACT(CELL("address",'Raw Data'!K10),"\$([A-Z]+)\$[0-9]+"))),_xlfn.REGEXEXTRACT(CELL("address",'Raw Data'!K10),"\$([A-Z]+)\$[0-9]+"))} | L10: {=IFERROR(IF(OR('Raw Data'!L10="",LEN(TRIM('Raw Data'!L10))=0),"",IF(AND(ISNUMBER('Raw Data'!L10), IFERROR('Raw Data'!L10 = ROUND('Raw Data'!L10, 2),FALSE)),"",_xlfn.REGEXEXTRACT(CELL("address",L10), "\$([A-Z]+)\$[0-9]+"))),_xlfn.REGEXEXTRACT(CELL("address",L10), "\$([A-Z]+)\$[0-9]+"))} | M10: {=IFERROR(IF(OR('Raw Data'!M10="",LEN(TRIM('Raw Data'!M10))=0),"",IF(AND(ISNUMBER('Raw Data'!M10), IFERROR('Raw Data'!M10 = ROUND('Raw Data'!M10, 2),FALSE)),"",_xlfn.REGEXEXTRACT(CELL("address",M10), "\$([A-Z]+)\$[0-9]+"))),_xlfn.REGEXEXTRACT(CELL("address",M10), "\$([A-Z]+)\$[0-9]+"))} | N10: {=IFERROR(IF(OR('Raw Data'!N10="",LEN(TRIM('Raw Data'!N10))=0),"",IF(AND(ISNUMBER('Raw Data'!N10), IFERROR('Raw Data'!N10 = ROUND('Raw Data'!N10, 2),FALSE)),"",_xlfn.REGEXEXTRACT(CELL("address",N10), "\$([A-Z]+)\$[0-9]+"))),_xlfn.REGEXEXTRACT(CELL("address",N10), "\$([A-Z]+)\$[0-9]+"))}
C11: {=IFERROR(IF(OR('Raw Data'!C11="",LEN(TRIM('Raw Data'!C11))=0),"",IF(AND(LEN('Raw Data'!C11) <= 20,LEN('Raw Data'!C11)> 0),"",_xlfn.REGEXEXTRACT(CELL("address",'Raw Data'!C11),"\$([A-Z]+)\$[0-9]+"))),_xlfn.REGEXEXTRACT(CELL("address",'Raw Data'!C11),"\$([A-Z]+)\$[0-9]+"))} | D11: {=IFERROR(IF(OR('Raw Data'!D11="",LEN(TRIM('Raw Data'!D11))=0),"",IF(AND(LEN('Raw Data'!D11) <= 255,LEN('Raw Data'!D11)> 0),"",_xlfn.REGEXEXTRACT(CELL("address",'Raw Data'!D11),"\$([A-Z]+)\$[0-9]+"))),_xlfn.REGEXEXTRACT(CELL("address",'Raw Data'!D11),"\$([A-Z]+)\$[0-9]+"))} | E11: {=IFERROR(IF(OR('Raw Data'!E11="",LEN(TRIM('Raw Data'!E11))=0),"",IF(AND(LEN('Raw Data'!E11) <= 255,LEN('Raw Data'!E11)> 0),"",_xlfn.REGEXEXTRACT(CELL("address",'Raw Data'!E11),"\$([A-Z]+)\$[0-9]+"))),_xlfn.REGEXEXTRACT(CELL("address",'Raw Data'!E11),"\$([A-Z]+)\$[0-9]+"))} | F11: {=IFERROR(IF(OR('Raw Data'!F11="",LEN(TRIM('Raw Data'!F11))=0),"",IF(AND(LEN('Raw Data'!F11) <= 50,LEN('Raw Data'!F11)> 0),"",_xlfn.REGEXEXTRACT(CELL("address",'Raw Data'!F11),"\$([A-Z]+)\$[0-9]+"))),_xlfn.REGEXEXTRACT(CELL("address",'Raw Data'!F11),"\$([A-Z]+)\$[0-9]+"))} | G11: {=IFERROR(IF(OR('Raw Data'!G11="",LEN(TRIM('Raw Data'!G11))=0),"",IF(AND(LEN('Raw Data'!G11) <= 255,LEN('Raw Data'!G11)> 0),"",_xlfn.REGEXEXTRACT(CELL("address",'Raw Data'!G11),"\$([A-Z]+)\$[0-9]+"))),_xlfn.REGEXEXTRACT(CELL("address",'Raw Data'!G11),"\$([A-Z]+)\$[0-9]+"))} | H11: {=IFERROR(IF(OR('Raw Data'!H11="",LEN(TRIM('Raw Data'!H11))=0),"",IF(AND(LEN('Raw Data'!H11) <= 255,LEN('Raw Data'!H11)> 0),"",_xlfn.REGEXEXTRACT(CELL("address",'Raw Data'!H11),"\$([A-Z]+)\$[0-9]+"))),_xlfn.REGEXEXTRACT(CELL("address",'Raw Data'!H11),"\$([A-Z]+)\$[0-9]+"))} | I11: {=IFERROR(IF(OR('Raw Data'!I11="",LEN(TRIM('Raw Data'!I11))=0),"",IF(AND(LEN('Raw Data'!I11) <= 255,LEN('Raw Data'!I11)> 0),"",_xlfn.REGEXEXTRACT(CELL("address",'Raw Data'!I11),"\$([A-Z]+)\$[0-9]+"))),_xlfn.REGEXEXTRACT(CELL("address",'Raw Data'!I11),"\$([A-Z]+)\$[0-9]+"))} | J11: {=IFERROR(IF(OR('Raw Data'!J11="",LEN(TRIM('Raw Data'!J11))=0),"",IF(AND(LEN('Raw Data'!J11) <= 255,LEN('Raw Data'!J11)> 0),"",_xlfn.REGEXEXTRACT(CELL("address",'Raw Data'!J11),"\$([A-Z]+)\$[0-9]+"))),_xlfn.REGEXEXTRACT(CELL("address",'Raw Data'!J11),"\$([A-Z]+)\$[0-9]+"))} | K11: {=IFERROR(IF(OR('Raw Data'!K11="",LEN(TRIM('Raw Data'!K11))=0),"",IF(AND(LEN('Raw Data'!K11) <= 10,LEN('Raw Data'!K11)> 0),"",_xlfn.REGEXEXTRACT(CELL("address",'Raw Data'!K11),"\$([A-Z]+)\$[0-9]+"))),_xlfn.REGEXEXTRACT(CELL("address",'Raw Data'!K11),"\$([A-Z]+)\$[0-9]+"))} | L11: {=IFERROR(IF(OR('Raw Data'!L11="",LEN(TRIM('Raw Data'!L11))=0),"",IF(AND(ISNUMBER('Raw Data'!L11), IFERROR('Raw Data'!L11 = ROUND('Raw Data'!L11, 2),FALSE)),"",_xlfn.REGEXEXTRACT(CELL("address",L11), "\$([A-Z]+)\$[0-9]+"))),_xlfn.REGEXEXTRACT(CELL("address",L11), "\$([A-Z]+)\$[0-9]+"))} | M11: {=IFERROR(IF(OR('Raw Data'!M11="",LEN(TRIM('Raw Data'!M11))=0),"",IF(AND(ISNUMBER('Raw Data'!M11), IFERROR('Raw Data'!M11 = ROUND('Raw Data'!M11, 2),FALSE)),"",_xlfn.REGEXEXTRACT(CELL("address",M11), "\$([A-Z]+)\$[0-9]+"))),_xlfn.REGEXEXTRACT(CELL("address",M11), "\$([A-Z]+)\$[0-9]+"))} | N11: {=IFERROR(IF(OR('Raw Data'!N11="",LEN(TRIM('Raw Data'!N11))=0),"",IF(AND(ISNUMBER('Raw Data'!N11), IFERROR('Raw Data'!N11 = ROUND('Raw Data'!N11, 2),FALSE)),"",_xlfn.REGEXEXTRACT(CELL("address",N11), "\$([A-Z]+)\$[0-9]+"))),_xlfn.REGEXEXTRACT(CELL("address",N11), "\$([A-Z]+)\$[0-9]+"))}
C12: {=IFERROR(IF(OR('Raw Data'!C12="",LEN(TRIM('Raw Data'!C12))=0),"",IF(AND(LEN('Raw Data'!C12) <= 20,LEN('Raw Data'!C12)> 0),"",_xlfn.REGEXEXTRACT(CELL("address",'Raw Data'!C12),"\$([A-Z]+)\$[0-9]+"))),_xlfn.REGEXEXTRACT(CELL("address",'Raw Data'!C12),"\$([A-Z]+)\$[0-9]+"))} | D12: {=IFERROR(IF(OR('Raw Data'!D12="",LEN(TRIM('Raw Data'!D12))=0),"",IF(AND(LEN('Raw Data'!D12) <= 255,LEN('Raw Data'!D12)> 0),"",_xlfn.REGEXEXTRACT(CELL("address",'Raw Data'!D12),"\$([A-Z]+)\$[0-9]+"))),_xlfn.REGEXEXTRACT(CELL("address",'Raw Data'!D12),"\$([A-Z]+)\$[0-9]+"))} | E12: {=IFERROR(IF(OR('Raw Data'!E12="",LEN(TRIM('Raw Data'!E12))=0),"",IF(AND(LEN('Raw Data'!E12) <= 255,LEN('Raw Data'!E12)> 0),"",_xlfn.REGEXEXTRACT(CELL("address",'Raw Data'!E12),"\$([A-Z]+)\$[0-9]+"))),_xlfn.REGEXEXTRACT(CELL("address",'Raw Data'!E12),"\$([A-Z]+)\$[0-9]+"))} | F12: {=IFERROR(IF(OR('Raw Data'!F12="",LEN(TRIM('Raw Data'!F12))=0),"",IF(AND(LEN('Raw Data'!F12) <= 50,LEN('Raw Data'!F12)> 0),"",_xlfn.REGEXEXTRACT(CELL("address",'Raw Data'!F12),"\$([A-Z]+)\$[0-9]+"))),_xlfn.REGEXEXTRACT(CELL("address",'Raw Data'!F12),"\$([A-Z]+)\$[0-9]+"))} | G12: {=IFERROR(IF(OR('Raw Data'!G12="",LEN(TRIM('Raw Data'!G12))=0),"",IF(AND(LEN('Raw Data'!G12) <= 255,LEN('Raw Data'!G12)> 0),"",_xlfn.REGEXEXTRACT(CELL("address",'Raw Data'!G12),"\$([A-Z]+)\$[0-9]+"))),_xlfn.REGEXEXTRACT(CELL("address",'Raw Data'!G12),"\$([A-Z]+)\$[0-9]+"))} | H12: {=IFERROR(IF(OR('Raw Data'!H12="",LEN(TRIM('Raw Data'!H12))=0),"",IF(AND(LEN('Raw Data'!H12) <= 255,LEN('Raw Data'!H12)> 0),"",_xlfn.REGEXEXTRACT(CELL("address",'Raw Data'!H12),"\$([A-Z]+)\$[0-9]+"))),_xlfn.REGEXEXTRACT(CELL("address",'Raw Data'!H12),"\$([A-Z]+)\$[0-9]+"))} | I12: {=IFERROR(IF(OR('Raw Data'!I12="",LEN(TRIM('Raw Data'!I12))=0),"",IF(AND(LEN('Raw Data'!I12) <= 255,LEN('Raw Data'!I12)> 0),"",_xlfn.REGEXEXTRACT(CELL("address",'Raw Data'!I12),"\$([A-Z]+)\$[0-9]+"))),_xlfn.REGEXEXTRACT(CELL("address",'Raw Data'!I12),"\$([A-Z]+)\$[0-9]+"))} | J12: {=IFERROR(IF(OR('Raw Data'!J12="",LEN(TRIM('Raw Data'!J12))=0),"",IF(AND(LEN('Raw Data'!J12) <= 255,LEN('Raw Data'!J12)> 0),"",_xlfn.REGEXEXTRACT(CELL("address",'Raw Data'!J12),"\$([A-Z]+)\$[0-9]+"))),_xlfn.REGEXEXTRACT(CELL("address",'Raw Data'!J12),"\$([A-Z]+)\$[0-9]+"))} | K12: {=IFERROR(IF(OR('Raw Data'!K12="",LEN(TRIM('Raw Data'!K12))=0),"",IF(AND(LEN('Raw Data'!K12) <= 10,LEN('Raw Data'!K12)> 0),"",_xlfn.REGEXEXTRACT(CELL("address",'Raw Data'!K12),"\$([A-Z]+)\$[0-9]+"))),_xlfn.REGEXEXTRACT(CELL("address",'Raw Data'!K12),"\$([A-Z]+)\$[0-9]+"))} | L12: {=IFERROR(IF(OR('Raw Data'!L12="",LEN(TRIM('Raw Data'!L12))=0),"",IF(AND(ISNUMBER('Raw Data'!L12), IFERROR('Raw Data'!L12 = ROUND('Raw Data'!L12, 2),FALSE)),"",_xlfn.REGEXEXTRACT(CELL("address",L12), "\$([A-Z]+)\$[0-9]+"))),_xlfn.REGEXEXTRACT(CELL("address",L12), "\$([A-Z]+)\$[0-9]+"))} | M12: {=IFERROR(IF(OR('Raw Data'!M12="",LEN(TRIM('Raw Data'!M12))=0),"",IF(AND(ISNUMBER('Raw Data'!M12), IFERROR('Raw Data'!M12 = ROUND('Raw Data'!M12, 2),FALSE)),"",_xlfn.REGEXEXTRACT(CELL("address",M12), "\$([A-Z]+)\$[0-9]+"))),_xlfn.REGEXEXTRACT(CELL("address",M12), "\$([A-Z]+)\$[0-9]+"))} | N12: {=IFERROR(IF(OR('Raw Data'!N12="",LEN(TRIM('Raw Data'!N12))=0),"",IF(AND(ISNUMBER('Raw Data'!N12), IFERROR('Raw Data'!N12 = ROUND('Raw Data'!N12, 2),FALSE)),"",_xlfn.REGEXEXTRACT(CELL("address",N12), "\$([A-Z]+)\$[0-9]+"))),_xlfn.REGEXEXTRACT(CELL("address",N12), "\$([A-Z]+)\$[0-9]+"))}
C13: {=IFERROR(IF(OR('Raw Data'!C13="",LEN(TRIM('Raw Data'!C13))=0),"",IF(AND(LEN('Raw Data'!C13) <= 20,LEN('Raw Data'!C13)> 0),"",_xlfn.REGEXEXTRACT(CELL("address",'Raw Data'!C13),"\$([A-Z]+)\$[0-9]+"))),_xlfn.REGEXEXTRACT(CELL("address",'Raw Data'!C13),"\$([A-Z]+)\$[0-9]+"))} | D13: {=IFERROR(IF(OR('Raw Data'!D13="",LEN(TRIM('Raw Data'!D13))=0),"",IF(AND(LEN('Raw Data'!D13) <= 255,LEN('Raw Data'!D13)> 0),"",_xlfn.REGEXEXTRACT(CELL("address",'Raw Data'!D13),"\$([A-Z]+)\$[0-9]+"))),_xlfn.REGEXEXTRACT(CELL("address",'Raw Data'!D13),"\$([A-Z]+)\$[0-9]+"))} | E13: {=IFERROR(IF(OR('Raw Data'!E13="",LEN(TRIM('Raw Data'!E13))=0),"",IF(AND(LEN('Raw Data'!E13) <= 255,LEN('Raw Data'!E13)> 0),"",_xlfn.REGEXEXTRACT(CELL("address",'Raw Data'!E13),"\$([A-Z]+)\$[0-9]+"))),_xlfn.REGEXEXTRACT(CELL("address",'Raw Data'!E13),"\$([A-Z]+)\$[0-9]+"))} | F13: {=IFERROR(IF(OR('Raw Data'!F13="",LEN(TRIM('Raw Data'!F13))=0),"",IF(AND(LEN('Raw Data'!F13) <= 50,LEN('Raw Data'!F13)> 0),"",_xlfn.REGEXEXTRACT(CELL("address",'Raw Data'!F13),"\$([A-Z]+)\$[0-9]+"))),_xlfn.REGEXEXTRACT(CELL("address",'Raw Data'!F13),"\$([A-Z]+)\$[0-9]+"))} | G13: {=IFERROR(IF(OR('Raw Data'!G13="",LEN(TRIM('Raw Data'!G13))=0),"",IF(AND(LEN('Raw Data'!G13) <= 255,LEN('Raw Data'!G13)> 0),"",_xlfn.REGEXEXTRACT(CELL("address",'Raw Data'!G13),"\$([A-Z]+)\$[0-9]+"))),_xlfn.REGEXEXTRACT(CELL("address",'Raw Data'!G13),"\$([A-Z]+)\$[0-9]+"))} | H13: {=IFERROR(IF(OR('Raw Data'!H13="",LEN(TRIM('Raw Data'!H13))=0),"",IF(AND(LEN('Raw Data'!H13) <= 255,LEN('Raw Data'!H13)> 0),"",_xlfn.REGEXEXTRACT(CELL("address",'Raw Data'!H13),"\$([A-Z]+)\$[0-9]+"))),_xlfn.REGEXEXTRACT(CELL("address",'Raw Data'!H13),"\$([A-Z]+)\$[0-9]+"))} | I13: {=IFERROR(IF(OR('Raw Data'!I13="",LEN(TRIM('Raw Data'!I13))=0),"",IF(AND(LEN('Raw Data'!I13) <= 255,LEN('Raw Data'!I13)> 0),"",_xlfn.REGEXEXTRACT(CELL("address",'Raw Data'!I13),"\$([A-Z]+)\$[0-9]+"))),_xlfn.REGEXEXTRACT(CELL("address",'Raw Data'!I13),"\$([A-Z]+)\$[0-9]+"))} | J13: {=IFERROR(IF(OR('Raw Data'!J13="",LEN(TRIM('Raw Data'!J13))=0),"",IF(AND(LEN('Raw Data'!J13) <= 255,LEN('Raw Data'!J13)> 0),"",_xlfn.REGEXEXTRACT(CELL("address",'Raw Data'!J13),"\$([A-Z]+)\$[0-9]+"))),_xlfn.REGEXEXTRACT(CELL("address",'Raw Data'!J13),"\$([A-Z]+)\$[0-9]+"))} | K13: {=IFERROR(IF(OR('Raw Data'!K13="",LEN(TRIM('Raw Data'!K13))=0),"",IF(AND(LEN('Raw Data'!K13) <= 10,LEN('Raw Data'!K13)> 0),"",_xlfn.REGEXEXTRACT(CELL("address",'Raw Data'!K13),"\$([A-Z]+)\$[0-9]+"))),_xlfn.REGEXEXTRACT(CELL("address",'Raw Data'!K13),"\$([A-Z]+)\$[0-9]+"))} | L13: {=IFERROR(IF(OR('Raw Data'!L13="",LEN(TRIM('Raw Data'!L13))=0),"",IF(AND(ISNUMBER('Raw Data'!L13), IFERROR('Raw Data'!L13 = ROUND('Raw Data'!L13, 2),FALSE)),"",_xlfn.REGEXEXTRACT(CELL("address",L13), "\$([A-Z]+)\$[0-9]+"))),_xlfn.REGEXEXTRACT(CELL("address",L13), "\$([A-Z]+)\$[0-9]+"))} | M13: {=IFERROR(IF(OR('Raw Data'!M13="",LEN(TRIM('Raw Data'!M13))=0),"",IF(AND(ISNUMBER('Raw Data'!M13), IFERROR('Raw Data'!M13 = ROUND('Raw Data'!M13, 2),FALSE)),"",_xlfn.REGEXEXTRACT(CELL("address",M13), "\$([A-Z]+)\$[0-9]+"))),_xlfn.REGEXEXTRACT(CELL("address",M13), "\$([A-Z]+)\$[0-9]+"))} | N13: {=IFERROR(IF(OR('Raw Data'!N13="",LEN(TRIM('Raw Data'!N13))=0),"",IF(AND(ISNUMBER('Raw Data'!N13), IFERROR('Raw Data'!N13 = ROUND('Raw Data'!N13, 2),FALSE)),"",_xlfn.REGEXEXTRACT(CELL("address",N13), "\$([A-Z]+)\$[0-9]+"))),_xlfn.REGEXEXTRACT(CELL("address",N13), "\$([A-Z]+)\$[0-9]+"))}
C14: {=IFERROR(IF(OR('Raw Data'!C14="",LEN(TRIM('Raw Data'!C14))=0),"",IF(AND(LEN('Raw Data'!C14) <= 20,LEN('Raw Data'!C14)> 0),"",_xlfn.REGEXEXTRACT(CELL("address",'Raw Data'!C14),"\$([A-Z]+)\$[0-9]+"))),_xlfn.REGEXEXTRACT(CELL("address",'Raw Data'!C14),"\$([A-Z]+)\$[0-9]+"))} | D14: {=IFERROR(IF(OR('Raw Data'!D14="",LEN(TRIM('Raw Data'!D14))=0),"",IF(AND(LEN('Raw Data'!D14) <= 255,LEN('Raw Data'!D14)> 0),"",_xlfn.REGEXEXTRACT(CELL("address",'Raw Data'!D14),"\$([A-Z]+)\$[0-9]+"))),_xlfn.REGEXEXTRACT(CELL("address",'Raw Data'!D14),"\$([A-Z]+)\$[0-9]+"))} | E14: {=IFERROR(IF(OR('Raw Data'!E14="",LEN(TRIM('Raw Data'!E14))=0),"",IF(AND(LEN('Raw Data'!E14) <= 255,LEN('Raw Data'!E14)> 0),"",_xlfn.REGEXEXTRACT(CELL("address",'Raw Data'!E14),"\$([A-Z]+)\$[0-9]+"))),_xlfn.REGEXEXTRACT(CELL("address",'Raw Data'!E14),"\$([A-Z]+)\$[0-9]+"))} | F14: {=IFERROR(IF(OR('Raw Data'!F14="",LEN(TRIM('Raw Data'!F14))=0),"",IF(AND(LEN('Raw Data'!F14) <= 50,LEN('Raw Data'!F14)> 0),"",_xlfn.REGEXEXTRACT(CELL("address",'Raw Data'!F14),"\$([A-Z]+)\$[0-9]+"))),_xlfn.REGEXEXTRACT(CELL("address",'Raw Data'!F14),"\$([A-Z]+)\$[0-9]+"))} | G14: {=IFERROR(IF(OR('Raw Data'!G14="",LEN(TRIM('Raw Data'!G14))=0),"",IF(AND(LEN('Raw Data'!G14) <= 255,LEN('Raw Data'!G14)> 0),"",_xlfn.REGEXEXTRACT(CELL("address",'Raw Data'!G14),"\$([A-Z]+)\$[0-9]+"))),_xlfn.REGEXEXTRACT(CELL("address",'Raw Data'!G14),"\$([A-Z]+)\$[0-9]+"))} | H14: {=IFERROR(IF(OR('Raw Data'!H14="",LEN(TRIM('Raw Data'!H14))=0),"",IF(AND(LEN('Raw Data'!H14) <= 255,LEN('Raw Data'!H14)> 0),"",_xlfn.REGEXEXTRACT(CELL("address",'Raw Data'!H14),"\$([A-Z]+)\$[0-9]+"))),_xlfn.REGEXEXTRACT(CELL("address",'Raw Data'!H14),"\$([A-Z]+)\$[0-9]+"))} | I14: {=IFERROR(IF(OR('Raw Data'!I14="",LEN(TRIM('Raw Data'!I14))=0),"",IF(AND(LEN('Raw Data'!I14) <= 255,LEN('Raw Data'!I14)> 0),"",_xlfn.REGEXEXTRACT(CELL("address",'Raw Data'!I14),"\$([A-Z]+)\$[0-9]+"))),_xlfn.REGEXEXTRACT(CELL("address",'Raw Data'!I14),"\$([A-Z]+)\$[0-9]+"))} | J14: {=IFERROR(IF(OR('Raw Data'!J14="",LEN(TRIM('Raw Data'!J14))=0),"",IF(AND(LEN('Raw Data'!J14) <= 255,LEN('Raw Data'!J14)> 0),"",_xlfn.REGEXEXTRACT(CELL("address",'Raw Data'!J14),"\$([A-Z]+)\$[0-9]+"))),_xlfn.REGEXEXTRACT(CELL("address",'Raw Data'!J14),"\$([A-Z]+)\$[0-9]+"))} | K14: {=IFERROR(IF(OR('Raw Data'!K14="",LEN(TRIM('Raw Data'!K14))=0),"",IF(AND(LEN('Raw Data'!K14) <= 10,LEN('Raw Data'!K14)> 0),"",_xlfn.REGEXEXTRACT(CELL("address",'Raw Data'!K14),"\$([A-Z]+)\$[0-9]+"))),_xlfn.REGEXEXTRACT(CELL("address",'Raw Data'!K14),"\$([A-Z]+)\$[0-9]+"))} | L14: {=IFERROR(IF(OR('Raw Data'!L14="",LEN(TRIM('Raw Data'!L14))=0),"",IF(AND(ISNUMBER('Raw Data'!L14), IFERROR('Raw Data'!L14 = ROUND('Raw Data'!L14, 2),FALSE)),"",_xlfn.REGEXEXTRACT(CELL("address",L14), "\$([A-Z]+)\$[0-9]+"))),_xlfn.REGEXEXTRACT(CELL("address",L14), "\$([A-Z]+)\$[0-9]+"))} | M14: {=IFERROR(IF(OR('Raw Data'!M14="",LEN(TRIM('Raw Data'!M14))=0),"",IF(AND(ISNUMBER('Raw Data'!M14), IFERROR('Raw Data'!M14 = ROUND('Raw Data'!M14, 2),FALSE)),"",_xlfn.REGEXEXTRACT(CELL("address",M14), "\$([A-Z]+)\$[0-9]+"))),_xlfn.REGEXEXTRACT(CELL("address",M14), "\$([A-Z]+)\$[0-9]+"))} | N14: {=IFERROR(IF(OR('Raw Data'!N14="",LEN(TRIM('Raw Data'!N14))=0),"",IF(AND(ISNUMBER('Raw Data'!N14), IFERROR('Raw Data'!N14 = ROUND('Raw Data'!N14, 2),FALSE)),"",_xlfn.REGEXEXTRACT(CELL("address",N14), "\$([A-Z]+)\$[0-9]+"))),_xlfn.REGEXEXTRACT(CELL("address",N14), "\$([A-Z]+)\$[0-9]+"))}
C15: {=IFERROR(IF(OR('Raw Data'!C15="",LEN(TRIM('Raw Data'!C15))=0),"",IF(AND(LEN('Raw Data'!C15) <= 20,LEN('Raw Data'!C15)> 0),"",_xlfn.REGEXEXTRACT(CELL("address",'Raw Data'!C15),"\$([A-Z]+)\$[0-9]+"))),_xlfn.REGEXEXTRACT(CELL("address",'Raw Data'!C15),"\$([A-Z]+)\$[0-9]+"))} | D15: {=IFERROR(IF(OR('Raw Data'!D15="",LEN(TRIM('Raw Data'!D15))=0),"",IF(AND(LEN('Raw Data'!D15) <= 255,LEN('Raw Data'!D15)> 0),"",_xlfn.REGEXEXTRACT(CELL("address",'Raw Data'!D15),"\$([A-Z]+)\$[0-9]+"))),_xlfn.REGEXEXTRACT(CELL("address",'Raw Data'!D15),"\$([A-Z]+)\$[0-9]+"))} | E15: {=IFERROR(IF(OR('Raw Data'!E15="",LEN(TRIM('Raw Data'!E15))=0),"",IF(AND(LEN('Raw Data'!E15) <= 255,LEN('Raw Data'!E15)> 0),"",_xlfn.REGEXEXTRACT(CELL("address",'Raw Data'!E15),"\$([A-Z]+)\$[0-9]+"))),_xlfn.REGEXEXTRACT(CELL("address",'Raw Data'!E15),"\$([A-Z]+)\$[0-9]+"))} | F15: {=IFERROR(IF(OR('Raw Data'!F15="",LEN(TRIM('Raw Data'!F15))=0),"",IF(AND(LEN('Raw Data'!F15) <= 50,LEN('Raw Data'!F15)> 0),"",_xlfn.REGEXEXTRACT(CELL("address",'Raw Data'!F15),"\$([A-Z]+)\$[0-9]+"))),_xlfn.REGEXEXTRACT(CELL("address",'Raw Data'!F15),"\$([A-Z]+)\$[0-9]+"))} | G15: {=IFERROR(IF(OR('Raw Data'!G15="",LEN(TRIM('Raw Data'!G15))=0),"",IF(AND(LEN('Raw Data'!G15) <= 255,LEN('Raw Data'!G15)> 0),"",_xlfn.REGEXEXTRACT(CELL("address",'Raw Data'!G15),"\$([A-Z]+)\$[0-9]+"))),_xlfn.REGEXEXTRACT(CELL("address",'Raw Data'!G15),"\$([A-Z]+)\$[0-9]+"))} | H15: {=IFERROR(IF(OR('Raw Data'!H15="",LEN(TRIM('Raw Data'!H15))=0),"",IF(AND(LEN('Raw Data'!H15) <= 255,LEN('Raw Data'!H15)> 0),"",_xlfn.REGEXEXTRACT(CELL("address",'Raw Data'!H15),"\$([A-Z]+)\$[0-9]+"))),_xlfn.REGEXEXTRACT(CELL("address",'Raw Data'!H15),"\$([A-Z]+)\$[0-9]+"))} | I15: {=IFERROR(IF(OR('Raw Data'!I15="",LEN(TRIM('Raw Data'!I15))=0),"",IF(AND(LEN('Raw Data'!I15) <= 255,LEN('Raw Data'!I15)> 0),"",_xlfn.REGEXEXTRACT(CELL("address",'Raw Data'!I15),"\$([A-Z]+)\$[0-9]+"))),_xlfn.REGEXEXTRACT(CELL("address",'Raw Data'!I15),"\$([A-Z]+)\$[0-9]+"))} | J15: {=IFERROR(IF(OR('Raw Data'!J15="",LEN(TRIM('Raw Data'!J15))=0),"",IF(AND(LEN('Raw Data'!J15) <= 255,LEN('Raw Data'!J15)> 0),"",_xlfn.REGEXEXTRACT(CELL("address",'Raw Data'!J15),"\$([A-Z]+)\$[0-9]+"))),_xlfn.REGEXEXTRACT(CELL("address",'Raw Data'!J15),"\$([A-Z]+)\$[0-9]+"))} | K15: {=IFERROR(IF(OR('Raw Data'!K15="",LEN(TRIM('Raw Data'!K15))=0),"",IF(AND(LEN('Raw Data'!K15) <= 10,LEN('Raw Data'!K15)> 0),"",_xlfn.REGEXEXTRACT(CELL("address",'Raw Data'!K15),"\$([A-Z]+)\$[0-9]+"))),_xlfn.REGEXEXTRACT(CELL("address",'Raw Data'!K15),"\$([A-Z]+)\$[0-9]+"))} | L15: {=IFERROR(IF(OR('Raw Data'!L15="",LEN(TRIM('Raw Data'!L15))=0),"",IF(AND(ISNUMBER('Raw Data'!L15), IFERROR('Raw Data'!L15 = ROUND('Raw Data'!L15, 2),FALSE)),"",_xlfn.REGEXEXTRACT(CELL("address",L15), "\$([A-Z]+)\$[0-9]+"))),_xlfn.REGEXEXTRACT(CELL("address",L15), "\$([A-Z]+)\$[0-9]+"))} | M15: {=IFERROR(IF(OR('Raw Data'!M15="",LEN(TRIM('Raw Data'!M15))=0),"",IF(AND(ISNUMBER('Raw Data'!M15), IFERROR('Raw Data'!M15 = ROUND('Raw Data'!M15, 2),FALSE)),"",_xlfn.REGEXEXTRACT(CELL("address",M15), "\$([A-Z]+)\$[0-9]+"))),_xlfn.REGEXEXTRACT(CELL("address",M15), "\$([A-Z]+)\$[0-9]+"))} | N15: {=IFERROR(IF(OR('Raw Data'!N15="",LEN(TRIM('Raw Data'!N15))=0),"",IF(AND(ISNUMBER('Raw Data'!N15), IFERROR('Raw Data'!N15 = ROUND('Raw Data'!N15, 2),FALSE)),"",_xlfn.REGEXEXTRACT(CELL("address",N15), "\$([A-Z]+)\$[0-9]+"))),_xlfn.REGEXEXTRACT(CELL("address",N15), "\$([A-Z]+)\$[0-9]+"))}
C16: {=IFERROR(IF(OR('Raw Data'!C16="",LEN(TRIM('Raw Data'!C16))=0),"",IF(AND(LEN('Raw Data'!C16) <= 20,LEN('Raw Data'!C16)> 0),"",_xlfn.REGEXEXTRACT(CELL("address",'Raw Data'!C16),"\$([A-Z]+)\$[0-9]+"))),_xlfn.REGEXEXTRACT(CELL("address",'Raw Data'!C16),"\$([A-Z]+)\$[0-9]+"))} | D16: {=IFERROR(IF(OR('Raw Data'!D16="",LEN(TRIM('Raw Data'!D16))=0),"",IF(AND(LEN('Raw Data'!D16) <= 255,LEN('Raw Data'!D16)> 0),"",_xlfn.REGEXEXTRACT(CELL("address",'Raw Data'!D16),"\$([A-Z]+)\$[0-9]+"))),_xlfn.REGEXEXTRACT(CELL("address",'Raw Data'!D16),"\$([A-Z]+)\$[0-9]+"))} | E16: {=IFERROR(IF(OR('Raw Data'!E16="",LEN(TRIM('Raw Data'!E16))=0),"",IF(AND(LEN('Raw Data'!E16) <= 255,LEN('Raw Data'!E16)> 0),"",_xlfn.REGEXEXTRACT(CELL("address",'Raw Data'!E16),"\$([A-Z]+)\$[0-9]+"))),_xlfn.REGEXEXTRACT(CELL("address",'Raw Data'!E16),"\$([A-Z]+)\$[0-9]+"))} | F16: {=IFERROR(IF(OR('Raw Data'!F16="",LEN(TRIM('Raw Data'!F16))=0),"",IF(AND(LEN('Raw Data'!F16) <= 50,LEN('Raw Data'!F16)> 0),"",_xlfn.REGEXEXTRACT(CELL("address",'Raw Data'!F16),"\$([A-Z]+)\$[0-9]+"))),_xlfn.REGEXEXTRACT(CELL("address",'Raw Data'!F16),"\$([A-Z]+)\$[0-9]+"))} | G16: {=IFERROR(IF(OR('Raw Data'!G16="",LEN(TRIM('Raw Data'!G16))=0),"",IF(AND(LEN('Raw Data'!G16) <= 255,LEN('Raw Data'!G16)> 0),"",_xlfn.REGEXEXTRACT(CELL("address",'Raw Data'!G16),"\$([A-Z]+)\$[0-9]+"))),_xlfn.REGEXEXTRACT(CELL("address",'Raw Data'!G16),"\$([A-Z]+)\$[0-9]+"))} | H16: {=IFERROR(IF(OR('Raw Data'!H16="",LEN(TRIM('Raw Data'!H16))=0),"",IF(AND(LEN('Raw Data'!H16) <= 255,LEN('Raw Data'!H16)> 0),"",_xlfn.REGEXEXTRACT(CELL("address",'Raw Data'!H16),"\$([A-Z]+)\$[0-9]+"))),_xlfn.REGEXEXTRACT(CELL("address",'Raw Data'!H16),"\$([A-Z]+)\$[0-9]+"))} | I16: {=IFERROR(IF(OR('Raw Data'!I16="",LEN(TRIM('Raw Data'!I16))=0),"",IF(AND(LEN('Raw Data'!I16) <= 255,LEN('Raw Data'!I16)> 0),"",_xlfn.REGEXEXTRACT(CELL("address",'Raw Data'!I16),"\$([A-Z]+)\$[0-9]+"))),_xlfn.REGEXEXTRACT(CELL("address",'Raw Data'!I16),"\$([A-Z]+)\$[0-9]+"))} | J16: {=IFERROR(IF(OR('Raw Data'!J16="",LEN(TRIM('Raw Data'!J16))=0),"",IF(AND(LEN('Raw Data'!J16) <= 255,LEN('Raw Data'!J16)> 0),"",_xlfn.REGEXEXTRACT(CELL("address",'Raw Data'!J16),"\$([A-Z]+)\$[0-9]+"))),_xlfn.REGEXEXTRACT(CELL("address",'Raw Data'!J16),"\$([A-Z]+)\$[0-9]+"))} | K16: {=IFERROR(IF(OR('Raw Data'!K16="",LEN(TRIM('Raw Data'!K16))=0),"",IF(AND(LEN('Raw Data'!K16) <= 10,LEN('Raw Data'!K16)> 0),"",_xlfn.REGEXEXTRACT(CELL("address",'Raw Data'!K16),"\$([A-Z]+)\$[0-9]+"))),_xlfn.REGEXEXTRACT(CELL("address",'Raw Data'!K16),"\$([A-Z]+)\$[0-9]+"))} | L16: {=IFERROR(IF(OR('Raw Data'!L16="",LEN(TRIM('Raw Data'!L16))=0),"",IF(AND(ISNUMBER('Raw Data'!L16), IFERROR('Raw Data'!L16 = ROUND('Raw Data'!L16, 2),FALSE)),"",_xlfn.REGEXEXTRACT(CELL("address",L16), "\$([A-Z]+)\$[0-9]+"))),_xlfn.REGEXEXTRACT(CELL("address",L16), "\$([A-Z]+)\$[0-9]+"))} | M16: {=IFERROR(IF(OR('Raw Data'!M16="",LEN(TRIM('Raw Data'!M16))=0),"",IF(AND(ISNUMBER('Raw Data'!M16), IFERROR('Raw Data'!M16 = ROUND('Raw Data'!M16, 2),FALSE)),"",_xlfn.REGEXEXTRACT(CELL("address",M16), "\$([A-Z]+)\$[0-9]+"))),_xlfn.REGEXEXTRACT(CELL("address",M16), "\$([A-Z]+)\$[0-9]+"))} | N16: {=IFERROR(IF(OR('Raw Data'!N16="",LEN(TRIM('Raw Data'!N16))=0),"",IF(AND(ISNUMBER('Raw Data'!N16), IFERROR('Raw Data'!N16 = ROUND('Raw Data'!N16, 2),FALSE)),"",_xlfn.REGEXEXTRACT(CELL("address",N16), "\$([A-Z]+)\$[0-9]+"))),_xlfn.REGEXEXTRACT(CELL("address",N16), "\$([A-Z]+)\$[0-9]+"))}
C17: {=IFERROR(IF(OR('Raw Data'!C17="",LEN(TRIM('Raw Data'!C17))=0),"",IF(AND(LEN('Raw Data'!C17) <= 20,LEN('Raw Data'!C17)> 0),"",_xlfn.REGEXEXTRACT(CELL("address",'Raw Data'!C17),"\$([A-Z]+)\$[0-9]+"))),_xlfn.REGEXEXTRACT(CELL("address",'Raw Data'!C17),"\$([A-Z]+)\$[0-9]+"))} | D17: {=IFERROR(IF(OR('Raw Data'!D17="",LEN(TRIM('Raw Data'!D17))=0),"",IF(AND(LEN('Raw Data'!D17) <= 255,LEN('Raw Data'!D17)> 0),"",_xlfn.REGEXEXTRACT(CELL("address",'Raw Data'!D17),"\$([A-Z]+)\$[0-9]+"))),_xlfn.REGEXEXTRACT(CELL("address",'Raw Data'!D17),"\$([A-Z]+)\$[0-9]+"))} | E17: {=IFERROR(IF(OR('Raw Data'!E17="",LEN(TRIM('Raw Data'!E17))=0),"",IF(AND(LEN('Raw Data'!E17) <= 255,LEN('Raw Data'!E17)> 0),"",_xlfn.REGEXEXTRACT(CELL("address",'Raw Data'!E17),"\$([A-Z]+)\$[0-9]+"))),_xlfn.REGEXEXTRACT(CELL("address",'Raw Data'!E17),"\$([A-Z]+)\$[0-9]+"))} | F17: {=IFERROR(IF(OR('Raw Data'!F17="",LEN(TRIM('Raw Data'!F17))=0),"",IF(AND(LEN('Raw Data'!F17) <= 50,LEN('Raw Data'!F17)> 0),"",_xlfn.REGEXEXTRACT(CELL("address",'Raw Data'!F17),"\$([A-Z]+)\$[0-9]+"))),_xlfn.REGEXEXTRACT(CELL("address",'Raw Data'!F17),"\$([A-Z]+)\$[0-9]+"))} | G17: {=IFERROR(IF(OR('Raw Data'!G17="",LEN(TRIM('Raw Data'!G17))=0),"",IF(AND(LEN('Raw Data'!G17) <= 255,LEN('Raw Data'!G17)> 0),"",_xlfn.REGEXEXTRACT(CELL("address",'Raw Data'!G17),"\$([A-Z]+)\$[0-9]+"))),_xlfn.REGEXEXTRACT(CELL("address",'Raw Data'!G17),"\$([A-Z]+)\$[0-9]+"))} | H17: {=IFERROR(IF(OR('Raw Data'!H17="",LEN(TRIM('Raw Data'!H17))=0),"",IF(AND(LEN('Raw Data'!H17) <= 255,LEN('Raw Data'!H17)> 0),"",_xlfn.REGEXEXTRACT(CELL("address",'Raw Data'!H17),"\$([A-Z]+)\$[0-9]+"))),_xlfn.REGEXEXTRACT(CELL("address",'Raw Data'!H17),"\$([A-Z]+)\$[0-9]+"))} | I17: {=IFERROR(IF(OR('Raw Data'!I17="",LEN(TRIM('Raw Data'!I17))=0),"",IF(AND(LEN('Raw Data'!I17) <= 255,LEN('Raw Data'!I17)> 0),"",_xlfn.REGEXEXTRACT(CELL("address",'Raw Data'!I17),"\$([A-Z]+)\$[0-9]+"))),_xlfn.REGEXEXTRACT(CELL("address",'Raw Data'!I17),"\$([A-Z]+)\$[0-9]+"))} | J17: {=IFERROR(IF(OR('Raw Data'!J17="",LEN(TRIM('Raw Data'!J17))=0),"",IF(AND(LEN('Raw Data'!J17) <= 255,LEN('Raw Data'!J17)> 0),"",_xlfn.REGEXEXTRACT(CELL("address",'Raw Data'!J17),"\$([A-Z]+)\$[0-9]+"))),_xlfn.REGEXEXTRACT(CELL("address",'Raw Data'!J17),"\$([A-Z]+)\$[0-9]+"))} | K17: {=IFERROR(IF(OR('Raw Data'!K17="",LEN(TRIM('Raw Data'!K17))=0),"",IF(AND(LEN('Raw Data'!K17) <= 10,LEN('Raw Data'!K17)> 0),"",_xlfn.REGEXEXTRACT(CELL("address",'Raw Data'!K17),"\$([A-Z]+)\$[0-9]+"))),_xlfn.REGEXEXTRACT(CELL("address",'Raw Data'!K17),"\$([A-Z]+)\$[0-9]+"))} | L17: {=IFERROR(IF(OR('Raw Data'!L17="",LEN(TRIM('Raw Data'!L17))=0),"",IF(AND(ISNUMBER('Raw Data'!L17), IFERROR('Raw Data'!L17 = ROUND('Raw Data'!L17, 2),FALSE)),"",_xlfn.REGEXEXTRACT(CELL("address",L17), "\$([A-Z]+)\$[0-9]+"))),_xlfn.REGEXEXTRACT(CELL("address",L17), "\$([A-Z]+)\$[0-9]+"))} | M17: {=IFERROR(IF(OR('Raw Data'!M17="",LEN(TRIM('Raw Data'!M17))=0),"",IF(AND(ISNUMBER('Raw Data'!M17), IFERROR('Raw Data'!M17 = ROUND('Raw Data'!M17, 2),FALSE)),"",_xlfn.REGEXEXTRACT(CELL("address",M17), "\$([A-Z]+)\$[0-9]+"))),_xlfn.REGEXEXTRACT(CELL("address",M17), "\$([A-Z]+)\$[0-9]+"))} | N17: {=IFERROR(IF(OR('Raw Data'!N17="",LEN(TRIM('Raw Data'!N17))=0),"",IF(AND(ISNUMBER('Raw Data'!N17), IFERROR('Raw Data'!N17 = ROUND('Raw Data'!N17, 2),FALSE)),"",_xlfn.REGEXEXTRACT(CELL("address",N17), "\$([A-Z]+)\$[0-9]+"))),_xlfn.REGEXEXTRACT(CELL("address",N17), "\$([A-Z]+)\$[0-9]+"))}
C18: {=IFERROR(IF(OR('Raw Data'!C18="",LEN(TRIM('Raw Data'!C18))=0),"",IF(AND(LEN('Raw Data'!C18) <= 20,LEN('Raw Data'!C18)> 0),"",_xlfn.REGEXEXTRACT(CELL("address",'Raw Data'!C18),"\$([A-Z]+)\$[0-9]+"))),_xlfn.REGEXEXTRACT(CELL("address",'Raw Data'!C18),"\$([A-Z]+)\$[0-9]+"))} | D18: {=IFERROR(IF(OR('Raw Data'!D18="",LEN(TRIM('Raw Data'!D18))=0),"",IF(AND(LEN('Raw Data'!D18) <= 255,LEN('Raw Data'!D18)> 0),"",_xlfn.REGEXEXTRACT(CELL("address",'Raw Data'!D18),"\$([A-Z]+)\$[0-9]+"))),_xlfn.REGEXEXTRACT(CELL("address",'Raw Data'!D18),"\$([A-Z]+)\$[0-9]+"))} | E18: {=IFERROR(IF(OR('Raw Data'!E18="",LEN(TRIM('Raw Data'!E18))=0),"",IF(AND(LEN('Raw Data'!E18) <= 255,LEN('Raw Data'!E18)> 0),"",_xlfn.REGEXEXTRACT(CELL("address",'Raw Data'!E18),"\$([A-Z]+)\$[0-9]+"))),_xlfn.REGEXEXTRACT(CELL("address",'Raw Data'!E18),"\$([A-Z]+)\$[0-9]+"))} | F18: {=IFERROR(IF(OR('Raw Data'!F18="",LEN(TRIM('Raw Data'!F18))=0),"",IF(AND(LEN('Raw Data'!F18) <= 50,LEN('Raw Data'!F18)> 0),"",_xlfn.REGEXEXTRACT(CELL("address",'Raw Data'!F18),"\$([A-Z]+)\$[0-9]+"))),_xlfn.REGEXEXTRACT(CELL("address",'Raw Data'!F18),"\$([A-Z]+)\$[0-9]+"))} | G18: {=IFERROR(IF(OR('Raw Data'!G18="",LEN(TRIM('Raw Data'!G18))=0),"",IF(AND(LEN('Raw Data'!G18) <= 255,LEN('Raw Data'!G18)> 0),"",_xlfn.REGEXEXTRACT(CELL("address",'Raw Data'!G18),"\$([A-Z]+)\$[0-9]+"))),_xlfn.REGEXEXTRACT(CELL("address",'Raw Data'!G18),"\$([A-Z]+)\$[0-9]+"))} | H18: {=IFERROR(IF(OR('Raw Data'!H18="",LEN(TRIM('Raw Data'!H18))=0),"",IF(AND(LEN('Raw Data'!H18) <= 255,LEN('Raw Data'!H18)> 0),"",_xlfn.REGEXEXTRACT(CELL("address",'Raw Data'!H18),"\$([A-Z]+)\$[0-9]+"))),_xlfn.REGEXEXTRACT(CELL("address",'Raw Data'!H18),"\$([A-Z]+)\$[0-9]+"))} | I18: {=IFERROR(IF(OR('Raw Data'!I18="",LEN(TRIM('Raw Data'!I18))=0),"",IF(AND(LEN('Raw Data'!I18) <= 255,LEN('Raw Data'!I18)> 0),"",_xlfn.REGEXEXTRACT(CELL("address",'Raw Data'!I18),"\$([A-Z]+)\$[0-9]+"))),_xlfn.REGEXEXTRACT(CELL("address",'Raw Data'!I18),"\$([A-Z]+)\$[0-9]+"))} | J18: {=IFERROR(IF(OR('Raw Data'!J18="",LEN(TRIM('Raw Data'!J18))=0),"",IF(AND(LEN('Raw Data'!J18) <= 255,LEN('Raw Data'!J18)> 0),"",_xlfn.REGEXEXTRACT(CELL("address",'Raw Data'!J18),"\$([A-Z]+)\$[0-9]+"))),_xlfn.REGEXEXTRACT(CELL("address",'Raw Data'!J18),"\$([A-Z]+)\$[0-9]+"))} | K18: {=IFERROR(IF(OR('Raw Data'!K18="",LEN(TRIM('Raw Data'!K18))=0),"",IF(AND(LEN('Raw Data'!K18) <= 10,LEN('Raw Data'!K18)> 0),"",_xlfn.REGEXEXTRACT(CELL("address",'Raw Data'!K18),"\$([A-Z]+)\$[0-9]+"))),_xlfn.REGEXEXTRACT(CELL("address",'Raw Data'!K18),"\$([A-Z]+)\$[0-9]+"))} | L18: {=IFERROR(IF(OR('Raw Data'!L18="",LEN(TRIM('Raw Data'!L18))=0),"",IF(AND(ISNUMBER('Raw Data'!L18), IFERROR('Raw Data'!L18 = ROUND('Raw Data'!L18, 2),FALSE)),"",_xlfn.REGEXEXTRACT(CELL("address",L18), "\$([A-Z]+)\$[0-9]+"))),_xlfn.REGEXEXTRACT(CELL("address",L18), "\$([A-Z]+)\$[0-9]+"))} | M18: {=IFERROR(IF(OR('Raw Data'!M18="",LEN(TRIM('Raw Data'!M18))=0),"",IF(AND(ISNUMBER('Raw Data'!M18), IFERROR('Raw Data'!M18 = ROUND('Raw Data'!M18, 2),FALSE)),"",_xlfn.REGEXEXTRACT(CELL("address",M18), "\$([A-Z]+)\$[0-9]+"))),_xlfn.REGEXEXTRACT(CELL("address",M18), "\$([A-Z]+)\$[0-9]+"))} | N18: {=IFERROR(IF(OR('Raw Data'!N18="",LEN(TRIM('Raw Data'!N18))=0),"",IF(AND(ISNUMBER('Raw Data'!N18), IFERROR('Raw Data'!N18 = ROUND('Raw Data'!N18, 2),FALSE)),"",_xlfn.REGEXEXTRACT(CELL("address",N18), "\$([A-Z]+)\$[0-9]+"))),_xlfn.REGEXEXTRACT(CELL("address",N18), "\$([A-Z]+)\$[0-9]+"))}
C19: {=IFERROR(IF(OR('Raw Data'!C19="",LEN(TRIM('Raw Data'!C19))=0),"",IF(AND(LEN('Raw Data'!C19) <= 20,LEN('Raw Data'!C19)> 0),"",_xlfn.REGEXEXTRACT(CELL("address",'Raw Data'!C19),"\$([A-Z]+)\$[0-9]+"))),_xlfn.REGEXEXTRACT(CELL("address",'Raw Data'!C19),"\$([A-Z]+)\$[0-9]+"))} | D19: {=IFERROR(IF(OR('Raw Data'!D19="",LEN(TRIM('Raw Data'!D19))=0),"",IF(AND(LEN('Raw Data'!D19) <= 255,LEN('Raw Data'!D19)> 0),"",_xlfn.REGEXEXTRACT(CELL("address",'Raw Data'!D19),"\$([A-Z]+)\$[0-9]+"))),_xlfn.REGEXEXTRACT(CELL("address",'Raw Data'!D19),"\$([A-Z]+)\$[0-9]+"))} | E19: {=IFERROR(IF(OR('Raw Data'!E19="",LEN(TRIM('Raw Data'!E19))=0),"",IF(AND(LEN('Raw Data'!E19) <= 255,LEN('Raw Data'!E19)> 0),"",_xlfn.REGEXEXTRACT(CELL("address",'Raw Data'!E19),"\$([A-Z]+)\$[0-9]+"))),_xlfn.REGEXEXTRACT(CELL("address",'Raw Data'!E19),"\$([A-Z]+)\$[0-9]+"))} | F19: {=IFERROR(IF(OR('Raw Data'!F19="",LEN(TRIM('Raw Data'!F19))=0),"",IF(AND(LEN('Raw Data'!F19) <= 50,LEN('Raw Data'!F19)> 0),"",_xlfn.REGEXEXTRACT(CELL("address",'Raw Data'!F19),"\$([A-Z]+)\$[0-9]+"))),_xlfn.REGEXEXTRACT(CELL("address",'Raw Data'!F19),"\$([A-Z]+)\$[0-9]+"))} | G19: {=IFERROR(IF(OR('Raw Data'!G19="",LEN(TRIM('Raw Data'!G19))=0),"",IF(AND(LEN('Raw Data'!G19) <= 255,LEN('Raw Data'!G19)> 0),"",_xlfn.REGEXEXTRACT(CELL("address",'Raw Data'!G19),"\$([A-Z]+)\$[0-9]+"))),_xlfn.REGEXEXTRACT(CELL("address",'Raw Data'!G19),"\$([A-Z]+)\$[0-9]+"))} | H19: {=IFERROR(IF(OR('Raw Data'!H19="",LEN(TRIM('Raw Data'!H19))=0),"",IF(AND(LEN('Raw Data'!H19) <= 255,LEN('Raw Data'!H19)> 0),"",_xlfn.REGEXEXTRACT(CELL("address",'Raw Data'!H19),"\$([A-Z]+)\$[0-9]+"))),_xlfn.REGEXEXTRACT(CELL("address",'Raw Data'!H19),"\$([A-Z]+)\$[0-9]+"))} | I19: {=IFERROR(IF(OR('Raw Data'!I19="",LEN(TRIM('Raw Data'!I19))=0),"",IF(AND(LEN('Raw Data'!I19) <= 255,LEN('Raw Data'!I19)> 0),"",_xlfn.REGEXEXTRACT(CELL("address",'Raw Data'!I19),"\$([A-Z]+)\$[0-9]+"))),_xlfn.REGEXEXTRACT(CELL("address",'Raw Data'!I19),"\$([A-Z]+)\$[0-9]+"))} | J19: {=IFERROR(IF(OR('Raw Data'!J19="",LEN(TRIM('Raw Data'!J19))=0),"",IF(AND(LEN('Raw Data'!J19) <= 255,LEN('Raw Data'!J19)> 0),"",_xlfn.REGEXEXTRACT(CELL("address",'Raw Data'!J19),"\$([A-Z]+)\$[0-9]+"))),_xlfn.REGEXEXTRACT(CELL("address",'Raw Data'!J19),"\$([A-Z]+)\$[0-9]+"))} | K19: {=IFERROR(IF(OR('Raw Data'!K19="",LEN(TRIM('Raw Data'!K19))=0),"",IF(AND(LEN('Raw Data'!K19) <= 10,LEN('Raw Data'!K19)> 0),"",_xlfn.REGEXEXTRACT(CELL("address",'Raw Data'!K19),"\$([A-Z]+)\$[0-9]+"))),_xlfn.REGEXEXTRACT(CELL("address",'Raw Data'!K19),"\$([A-Z]+)\$[0-9]+"))} | L19: {=IFERROR(IF(OR('Raw Data'!L19="",LEN(TRIM('Raw Data'!L19))=0),"",IF(AND(ISNUMBER('Raw Data'!L19), IFERROR('Raw Data'!L19 = ROUND('Raw Data'!L19, 2),FALSE)),"",_xlfn.REGEXEXTRACT(CELL("address",L19), "\$([A-Z]+)\$[0-9]+"))),_xlfn.REGEXEXTRACT(CELL("address",L19), "\$([A-Z]+)\$[0-9]+"))} | M19: {=IFERROR(IF(OR('Raw Data'!M19="",LEN(TRIM('Raw Data'!M19))=0),"",IF(AND(ISNUMBER('Raw Data'!M19), IFERROR('Raw Data'!M19 = ROUND('Raw Data'!M19, 2),FALSE)),"",_xlfn.REGEXEXTRACT(CELL("address",M19), "\$([A-Z]+)\$[0-9]+"))),_xlfn.REGEXEXTRACT(CELL("address",M19), "\$([A-Z]+)\$[0-9]+"))} | N19: {=IFERROR(IF(OR('Raw Data'!N19="",LEN(TRIM('Raw Data'!N19))=0),"",IF(AND(ISNUMBER('Raw Data'!N19), IFERROR('Raw Data'!N19 = ROUND('Raw Data'!N19, 2),FALSE)),"",_xlfn.REGEXEXTRACT(CELL("address",N19), "\$([A-Z]+)\$[0-9]+"))),_xlfn.REGEXEXTRACT(CELL("address",N19), "\$([A-Z]+)\$[0-9]+"))}
C20: {=IFERROR(IF(OR('Raw Data'!C20="",LEN(TRIM('Raw Data'!C20))=0),"",IF(AND(LEN('Raw Data'!C20) <= 20,LEN('Raw Data'!C20)> 0),"",_xlfn.REGEXEXTRACT(CELL("address",'Raw Data'!C20),"\$([A-Z]+)\$[0-9]+"))),_xlfn.REGEXEXTRACT(CELL("address",'Raw Data'!C20),"\$([A-Z]+)\$[0-9]+"))} | D20: {=IFERROR(IF(OR('Raw Data'!D20="",LEN(TRIM('Raw Data'!D20))=0),"",IF(AND(LEN('Raw Data'!D20) <= 255,LEN('Raw Data'!D20)> 0),"",_xlfn.REGEXEXTRACT(CELL("address",'Raw Data'!D20),"\$([A-Z]+)\$[0-9]+"))),_xlfn.REGEXEXTRACT(CELL("address",'Raw Data'!D20),"\$([A-Z]+)\$[0-9]+"))} | E20: {=IFERROR(IF(OR('Raw Data'!E20="",LEN(TRIM('Raw Data'!E20))=0),"",IF(AND(LEN('Raw Data'!E20) <= 255,LEN('Raw Data'!E20)> 0),"",_xlfn.REGEXEXTRACT(CELL("address",'Raw Data'!E20),"\$([A-Z]+)\$[0-9]+"))),_xlfn.REGEXEXTRACT(CELL("address",'Raw Data'!E20),"\$([A-Z]+)\$[0-9]+"))} | F20: {=IFERROR(IF(OR('Raw Data'!F20="",LEN(TRIM('Raw Data'!F20))=0),"",IF(AND(LEN('Raw Data'!F20) <= 50,LEN('Raw Data'!F20)> 0),"",_xlfn.REGEXEXTRACT(CELL("address",'Raw Data'!F20),"\$([A-Z]+)\$[0-9]+"))),_xlfn.REGEXEXTRACT(CELL("address",'Raw Data'!F20),"\$([A-Z]+)\$[0-9]+"))} | G20: {=IFERROR(IF(OR('Raw Data'!G20="",LEN(TRIM('Raw Data'!G20))=0),"",IF(AND(LEN('Raw Data'!G20) <= 255,LEN('Raw Data'!G20)> 0),"",_xlfn.REGEXEXTRACT(CELL("address",'Raw Data'!G20),"\$([A-Z]+)\$[0-9]+"))),_xlfn.REGEXEXTRACT(CELL("address",'Raw Data'!G20),"\$([A-Z]+)\$[0-9]+"))} | H20: {=IFERROR(IF(OR('Raw Data'!H20="",LEN(TRIM('Raw Data'!H20))=0),"",IF(AND(LEN('Raw Data'!H20) <= 255,LEN('Raw Data'!H20)> 0),"",_xlfn.REGEXEXTRACT(CELL("address",'Raw Data'!H20),"\$([A-Z]+)\$[0-9]+"))),_xlfn.REGEXEXTRACT(CELL("address",'Raw Data'!H20),"\$([A-Z]+)\$[0-9]+"))} | I20: {=IFERROR(IF(OR('Raw Data'!I20="",LEN(TRIM('Raw Data'!I20))=0),"",IF(AND(LEN('Raw Data'!I20) <= 255,LEN('Raw Data'!I20)> 0),"",_xlfn.REGEXEXTRACT(CELL("address",'Raw Data'!I20),"\$([A-Z]+)\$[0-9]+"))),_xlfn.REGEXEXTRACT(CELL("address",'Raw Data'!I20),"\$([A-Z]+)\$[0-9]+"))} | J20: {=IFERROR(IF(OR('Raw Data'!J20="",LEN(TRIM('Raw Data'!J20))=0),"",IF(AND(LEN('Raw Data'!J20) <= 255,LEN('Raw Data'!J20)> 0),"",_xlfn.REGEXEXTRACT(CELL("address",'Raw Data'!J20),"\$([A-Z]+)\$[0-9]+"))),_xlfn.REGEXEXTRACT(CELL("address",'Raw Data'!J20),"\$([A-Z]+)\$[0-9]+"))} | K20: {=IFERROR(IF(OR('Raw Data'!K20="",LEN(TRIM('Raw Data'!K20))=0),"",IF(AND(LEN('Raw Data'!K20) <= 10,LEN('Raw Data'!K20)> 0),"",_xlfn.REGEXEXTRACT(CELL("address",'Raw Data'!K20),"\$([A-Z]+)\$[0-9]+"))),_xlfn.REGEXEXTRACT(CELL("address",'Raw Data'!K20),"\$([A-Z]+)\$[0-9]+"))} | L20: {=IFERROR(IF(OR('Raw Data'!L20="",LEN(TRIM('Raw Data'!L20))=0),"",IF(AND(ISNUMBER('Raw Data'!L20), IFERROR('Raw Data'!L20 = ROUND('Raw Data'!L20, 2),FALSE)),"",_xlfn.REGEXEXTRACT(CELL("address",L20), "\$([A-Z]+)\$[0-9]+"))),_xlfn.REGEXEXTRACT(CELL("address",L20), "\$([A-Z]+)\$[0-9]+"))} | M20: {=IFERROR(IF(OR('Raw Data'!M20="",LEN(TRIM('Raw Data'!M20))=0),"",IF(AND(ISNUMBER('Raw Data'!M20), IFERROR('Raw Data'!M20 = ROUND('Raw Data'!M20, 2),FALSE)),"",_xlfn.REGEXEXTRACT(CELL("address",M20), "\$([A-Z]+)\$[0-9]+"))),_xlfn.REGEXEXTRACT(CELL("address",M20), "\$([A-Z]+)\$[0-9]+"))} | N20: {=IFERROR(IF(OR('Raw Data'!N20="",LEN(TRIM('Raw Data'!N20))=0),"",IF(AND(ISNUMBER('Raw Data'!N20), IFERROR('Raw Data'!N20 = ROUND('Raw Data'!N20, 2),FALSE)),"",_xlfn.REGEXEXTRACT(CELL("address",N20), "\$([A-Z]+)\$[0-9]+"))),_xlfn.REGEXEXTRACT(CELL("address",N20), "\$([A-Z]+)\$[0-9]+"))}
C21: {=IFERROR(IF(OR('Raw Data'!C21="",LEN(TRIM('Raw Data'!C21))=0),"",IF(AND(LEN('Raw Data'!C21) <= 20,LEN('Raw Data'!C21)> 0),"",_xlfn.REGEXEXTRACT(CELL("address",'Raw Data'!C21),"\$([A-Z]+)\$[0-9]+"))),_xlfn.REGEXEXTRACT(CELL("address",'Raw Data'!C21),"\$([A-Z]+)\$[0-9]+"))} | D21: {=IFERROR(IF(OR('Raw Data'!D21="",LEN(TRIM('Raw Data'!D21))=0),"",IF(AND(LEN('Raw Data'!D21) <= 255,LEN('Raw Data'!D21)> 0),"",_xlfn.REGEXEXTRACT(CELL("address",'Raw Data'!D21),"\$([A-Z]+)\$[0-9]+"))),_xlfn.REGEXEXTRACT(CELL("address",'Raw Data'!D21),"\$([A-Z]+)\$[0-9]+"))} | E21: {=IFERROR(IF(OR('Raw Data'!E21="",LEN(TRIM('Raw Data'!E21))=0),"",IF(AND(LEN('Raw Data'!E21) <= 255,LEN('Raw Data'!E21)> 0),"",_xlfn.REGEXEXTRACT(CELL("address",'Raw Data'!E21),"\$([A-Z]+)\$[0-9]+"))),_xlfn.REGEXEXTRACT(CELL("address",'Raw Data'!E21),"\$([A-Z]+)\$[0-9]+"))} | F21: {=IFERROR(IF(OR('Raw Data'!F21="",LEN(TRIM('Raw Data'!F21))=0),"",IF(AND(LEN('Raw Data'!F21) <= 50,LEN('Raw Data'!F21)> 0),"",_xlfn.REGEXEXTRACT(CELL("address",'Raw Data'!F21),"\$([A-Z]+)\$[0-9]+"))),_xlfn.REGEXEXTRACT(CELL("address",'Raw Data'!F21),"\$([A-Z]+)\$[0-9]+"))} | G21: {=IFERROR(IF(OR('Raw Data'!G21="",LEN(TRIM('Raw Data'!G21))=0),"",IF(AND(LEN('Raw Data'!G21) <= 255,LEN('Raw Data'!G21)> 0),"",_xlfn.REGEXEXTRACT(CELL("address",'Raw Data'!G21),"\$([A-Z]+)\$[0-9]+"))),_xlfn.REGEXEXTRACT(CELL("address",'Raw Data'!G21),"\$([A-Z]+)\$[0-9]+"))} | H21: {=IFERROR(IF(OR('Raw Data'!H21="",LEN(TRIM('Raw Data'!H21))=0),"",IF(AND(LEN('Raw Data'!H21) <= 255,LEN('Raw Data'!H21)> 0),"",_xlfn.REGEXEXTRACT(CELL("address",'Raw Data'!H21),"\$([A-Z]+)\$[0-9]+"))),_xlfn.REGEXEXTRACT(CELL("address",'Raw Data'!H21),"\$([A-Z]+)\$[0-9]+"))} | I21: {=IFERROR(IF(OR('Raw Data'!I21="",LEN(TRIM('Raw Data'!I21))=0),"",IF(AND(LEN('Raw Data'!I21) <= 255,LEN('Raw Data'!I21)> 0),"",_xlfn.REGEXEXTRACT(CELL("address",'Raw Data'!I21),"\$([A-Z]+)\$[0-9]+"))),_xlfn.REGEXEXTRACT(CELL("address",'Raw Data'!I21),"\$([A-Z]+)\$[0-9]+"))} | J21: {=IFERROR(IF(OR('Raw Data'!J21="",LEN(TRIM('Raw Data'!J21))=0),"",IF(AND(LEN('Raw Data'!J21) <= 255,LEN('Raw Data'!J21)> 0),"",_xlfn.REGEXEXTRACT(CELL("address",'Raw Data'!J21),"\$([A-Z]+)\$[0-9]+"))),_xlfn.REGEXEXTRACT(CELL("address",'Raw Data'!J21),"\$([A-Z]+)\$[0-9]+"))} | K21: {=IFERROR(IF(OR('Raw Data'!K21="",LEN(TRIM('Raw Data'!K21))=0),"",IF(AND(LEN('Raw Data'!K21) <= 10,LEN('Raw Data'!K21)> 0),"",_xlfn.REGEXEXTRACT(CELL("address",'Raw Data'!K21),"\$([A-Z]+)\$[0-9]+"))),_xlfn.REGEXEXTRACT(CELL("address",'Raw Data'!K21),"\$([A-Z]+)\$[0-9]+"))} | L21: {=IFERROR(IF(OR('Raw Data'!L21="",LEN(TRIM('Raw Data'!L21))=0),"",IF(AND(ISNUMBER('Raw Data'!L21), IFERROR('Raw Data'!L21 = ROUND('Raw Data'!L21, 2),FALSE)),"",_xlfn.REGEXEXTRACT(CELL("address",L21), "\$([A-Z]+)\$[0-9]+"))),_xlfn.REGEXEXTRACT(CELL("address",L21), "\$([A-Z]+)\$[0-9]+"))} | M21: {=IFERROR(IF(OR('Raw Data'!M21="",LEN(TRIM('Raw Data'!M21))=0),"",IF(AND(ISNUMBER('Raw Data'!M21), IFERROR('Raw Data'!M21 = ROUND('Raw Data'!M21, 2),FALSE)),"",_xlfn.REGEXEXTRACT(CELL("address",M21), "\$([A-Z]+)\$[0-9]+"))),_xlfn.REGEXEXTRACT(CELL("address",M21), "\$([A-Z]+)\$[0-9]+"))} | N21: {=IFERROR(IF(OR('Raw Data'!N21="",LEN(TRIM('Raw Data'!N21))=0),"",IF(AND(ISNUMBER('Raw Data'!N21), IFERROR('Raw Data'!N21 = ROUND('Raw Data'!N21, 2),FALSE)),"",_xlfn.REGEXEXTRACT(CELL("address",N21), "\$([A-Z]+)\$[0-9]+"))),_xlfn.REGEXEXTRACT(CELL("address",N21), "\$([A-Z]+)\$[0-9]+"))}
... C1259: {=IFERROR(IF(OR('Raw Data'!C1259="",LEN(TRIM('Raw Data'!C1259))=0),"",IF(AND(LEN('Raw Data'!C1259) <= 20,LEN('Raw Data'!C1259)> 0),"",_xlfn.REGEXEXTRACT(CELL("address",'Raw Data'!C1259),"\$([A-Z]+)\$[0-9]+"))),_xlfn.REGEXEXTRACT(CELL("address",'Raw Data'!C1259),"\$([A-Z]+)\$[0-9]+"))} | D1259: {=IFERROR(IF(OR('Raw Data'!D1259="",LEN(TRIM('Raw Data'!D1259))=0),"",IF(AND(LEN('Raw Data'!D1259) <= 255,LEN('Raw Data'!D1259)> 0),"",_xlfn.REGEXEXTRACT(CELL("address",'Raw Data'!D1259),"\$([A-Z]+)\$[0-9]+"))),_xlfn.REGEXEXTRACT(CELL("address",'Raw Data'!D1259),"\$([A-Z]+)\$[0-9]+"))} | E1259: {=IFERROR(IF(OR('Raw Data'!E1259="",LEN(TRIM('Raw Data'!E1259))=0),"",IF(AND(LEN('Raw Data'!E1259) <= 255,LEN('Raw Data'!E1259)> 0),"",_xlfn.REGEXEXTRACT(CELL("address",'Raw Data'!E1259),"\$([A-Z]+)\$[0-9]+"))),_xlfn.REGEXEXTRACT(CELL("address",'Raw Data'!E1259),"\$([A-Z]+)\$[0-9]+"))} | F1259: {=IFERROR(IF(OR('Raw Data'!F1259="",LEN(TRIM('Raw Data'!F1259))=0),"",IF(AND(LEN('Raw Data'!F1259) <= 50,LEN('Raw Data'!F1259)> 0),"",_xlfn.REGEXEXTRACT(CELL("address",'Raw Data'!F1259),"\$([A-Z]+)\$[0-9]+"))),_xlfn.REGEXEXTRACT(CELL("address",'Raw Data'!F1259),"\$([A-Z]+)\$[0-9]+"))} | G1259: {=IFERROR(IF(OR('Raw Data'!G1259="",LEN(TRIM('Raw Data'!G1259))=0),"",IF(AND(LEN('Raw Data'!G1259) <= 255,LEN('Raw Data'!G1259)> 0),"",_xlfn.REGEXEXTRACT(CELL("address",'Raw Data'!G1259),"\$([A-Z]+)\$[0-9]+"))),_xlfn.REGEXEXTRACT(CELL("address",'Raw Data'!G1259),"\$([A-Z]+)\$[0-9]+"))} | H1259: {=IFERROR(IF(OR('Raw Data'!H1259="",LEN(TRIM('Raw Data'!H1259))=0),"",IF(AND(LEN('Raw Data'!H1259) <= 255,LEN('Raw Data'!H1259)> 0),"",_xlfn.REGEXEXTRACT(CELL("address",'Raw Data'!H1259),"\$([A-Z]+)\$[0-9]+"))),_xlfn.REGEXEXTRACT(CELL("address",'Raw Data'!H1259),"\$([A-Z]+)\$[0-9]+"))} | I1259: {=IFERROR(IF(OR('Raw Data'!I1259="",LEN(TRIM('Raw Data'!I1259))=0),"",IF(AND(LEN('Raw Data'!I1259) <= 255,LEN('Raw Data'!I1259)> 0),"",_xlfn.REGEXEXTRACT(CELL("address",'Raw Data'!I1259),"\$([A-Z]+)\$[0-9]+"))),_xlfn.REGEXEXTRACT(CELL("address",'Raw Data'!I1259),"\$([A-Z]+)\$[0-9]+"))} | J1259: {=IFERROR(IF(OR('Raw Data'!J1259="",LEN(TRIM('Raw Data'!J1259))=0),"",IF(AND(LEN('Raw Data'!J1259) <= 255,LEN('Raw Data'!J1259)> 0),"",_xlfn.REGEXEXTRACT(CELL("address",'Raw Data'!J1259),"\$([A-Z]+)\$[0-9]+"))),_xlfn.REGEXEXTRACT(CELL("address",'Raw Data'!J1259),"\$([A-Z]+)\$[0-9]+"))} | K1259: {=IFERROR(IF(OR('Raw Data'!K1259="",LEN(TRIM('Raw Data'!K1259))=0),"",IF(AND(LEN('Raw Data'!K1259) <= 10,LEN('Raw Data'!K1259)> 0),"",_xlfn.REGEXEXTRACT(CELL("address",'Raw Data'!K1259),"\$([A-Z]+)\$[0-9]+"))),_xlfn.REGEXEXTRACT(CELL("address",'Raw Data'!K1259),"\$([A-Z]+)\$[0-9]+"))} | L1259: {=IFERROR(IF(OR('Raw Data'!L1259="",LEN(TRIM('Raw Data'!L1259))=0),"",IF(AND(ISNUMBER('Raw Data'!L1259), IFERROR('Raw Data'!L1259 = ROUND('Raw Data'!L1259, 2),FALSE)),"",_xlfn.REGEXEXTRACT(CELL("address",L1259), "\$([A-Z]+)\$[0-9]+"))),_xlfn.REGEXEXTRACT(CELL("address",L1259), "\$([A-Z]+)\$[0-9]+"))} | M1259: {=IFERROR(IF(OR('Raw Data'!M1259="",LEN(TRIM('Raw Data'!M1259))=0),"",IF(AND(ISNUMBER('Raw Data'!M1259), IFERROR('Raw Data'!M1259 = ROUND('Raw Data'!M1259, 2),FALSE)),"",_xlfn.REGEXEXTRACT(CELL("address",M1259), "\$([A-Z]+)\$[0-9]+"))),_xlfn.REGEXEXTRACT(CELL("address",M1259), "\$([A-Z]+)\$[0-9]+"))} | N1259: {=IFERROR(IF(OR('Raw Data'!N1259="",LEN(TRIM('Raw Data'!N1259))=0),"",IF(AND(ISNUMBER('Raw Data'!N1259), IFERROR('Raw Data'!N1259 = ROUND('Raw Data'!N1259, 2),FALSE)),"",_xlfn.REGEXEXTRACT(CELL("address",N1259), "\$([A-Z]+)\$[0-9]+"))),_xlfn.REGEXEXTRACT(CELL("address",N1259), "\$([A-Z]+)\$[0-9]+"))}

Sheet Configuration
A1: col_number | B1: range_start | C1: range_stop | D1: project_active_Start | E1: project_inactive_end | F1: relate_document
A2: 2 | B2: C10 | C2: N? | D2: 45292 | E2: 46388

Sheet Validate_Type
B1: C1 | C1: C2 | D1: C3 | E1: C4 | F1: C5 | G1: C6 | H1: C7 | I1: C8
B2: {=IF('Raw Data'!B1="",_xlfn.REGEXEXTRACT(CELL("address",'Raw Data'!B1),"\$([A-Z]+)\$[0-9]+"),"")} -> $B$1 | C2: {=IF('Raw Data'!C1="",_xlfn.REGEXEXTRACT(CELL("address",'Raw Data'!C1),"\$([A-Z]+)\$[0-9]+"),"")} -> $C$1 | D2: {=IF('Raw Data'!D1="",_xlfn.REGEXEXTRACT(CELL("address",'Raw Data'!D1),"\$([A-Z]+)\$[0-9]+"),"")} -> $D$1 | E2: {=IF('Raw Data'!E1="",_xlfn.REGEXEXTRACT(CELL("address",'Raw Data'!E1),"\$([A-Z]+)\$[0-9]+"),"")} -> $E$1 | F2: {=IF('Raw Data'!F1="",_xlfn.REGEXEXTRACT(CELL("address",'Raw Data'!F1),"\$([A-Z]+)\$[0-9]+"),"")} -> $F$1 | G2: {=IF('Raw Data'!G1="",_xlfn.REGEXEXTRACT(CELL("address",'Raw Data'!G1),"\$([A-Z]+)\$[0-9]+"),"")} -> $G$1 | H2: {=IF('Raw Data'!H1="",_xlfn.REGEXEXTRACT(CELL("address",'Raw Data'!H1),"\$([A-Z]+)\$[0-9]+"),"")} -> $H$1 | I2: {=IF('Raw Data'!I1="",_xlfn.REGEXEXTRACT(CELL("address",'Raw Data'!I1),"\$([A-Z]+)\$[0-9]+"),"")} -> $I$1
B3: {=IF('Raw Data'!B3="",_xlfn.REGEXEXTRACT(CELL("address",'Raw Data'!B3),"\$([A-Z]+)\$[0-9]+"),"")} -> $B$3 | C3: {=IF('Raw Data'!C3="",_xlfn.REGEXEXTRACT(CELL("address",'Raw Data'!C3),"\$([A-Z]+)\$[0-9]+"),"")} -> $C$3 | D3: {=IF('Raw Data'!D3="",_xlfn.REGEXEXTRACT(CELL("address",'Raw Data'!D3),"\$([A-Z]+)\$[0-9]+"),"")} -> $D$3 | E3: {=IF('Raw Data'!E3="",_xlfn.REGEXEXTRACT(CELL("address",'Raw Data'!E3),"\$([A-Z]+)\$[0-9]+"),"")} -> $E$3 | F3: {=IF('Raw Data'!F3="",_xlfn.REGEXEXTRACT(CELL("address",'Raw Data'!F3),"\$([A-Z]+)\$[0-9]+"),"")} -> $F$3 | G3: {=IF('Raw Data'!G3="",_xlfn.REGEXEXTRACT(CELL("address",'Raw Data'!G3),"\$([A-Z]+)\$[0-9]+"),"")} -> $G$3 | H3: {=IF('Raw Data'!H3="",_xlfn.REGEXEXTRACT(CELL("address",'Raw Data'!H3),"\$([A-Z]+)\$[0-9]+"),"")} -> $H$3 | I3: {=IF('Raw Data'!I3="",_xlfn.REGEXEXTRACT(CELL("address",'Raw Data'!I3),"\$([A-Z]+)\$[0-9]+"),"")} -> $I$3
B4: {=IF('Raw Data'!B4="",_xlfn.REGEXEXTRACT(CELL("address",'Raw Data'!B4),"\$([A-Z]+)\$[0-9]+"),"")} -> $B$4 | C4: {=IF('Raw Data'!C4="",_xlfn.REGEXEXTRACT(CELL("address",'Raw Data'!C4),"\$([A-Z]+)\$[0-9]+"),"")} -> $C$4 | D4: {=IF('Raw Data'!D4="",_xlfn.REGEXEXTRACT(CELL("address",'Raw Data'!D4),"\$([A-Z]+)\$[0-9]+"),"")} -> $D$4 | E4: {=IF('Raw Data'!E4="",_xlfn.REGEXEXTRACT(CELL("address",'Raw Data'!E4),"\$([A-Z]+)\$[0-9]+"),"")} -> $E$4 | F4: {=IF('Raw Data'!F4="",_xlfn.REGEXEXTRACT(CELL("address",'Raw Data'!F4),"\$([A-Z]+)\$[0-9]+"),"")} -> $F$4 | G4: {=IF('Raw Data'!G4="",_xlfn.REGEXEXTRACT(CELL("address",'Raw Data'!G4),"\$([A-Z]+)\$[0-9]+"),"")} -> $G$4 | H4: {=IF('Raw Data'!H4="",_xlfn.REGEXEXTRACT(CELL("address",'Raw Data'!H4),"\$([A-Z]+)\$[0-9]+"),"")} -> $H$4 | I4: {=IF('Raw Data'!I4="",_xlfn.REGEXEXTRACT(CELL("address",'Raw Data'!I4),"\$([A-Z]+)\$[0-9]+"),"")} -> $I$4
B5: {=IF('Raw Data'!B5="",_xlfn.REGEXEXTRACT(CELL("address",'Raw Data'!B5),"\$([A-Z]+)\$[0-9]+"),"")} -> $B$5 | C5: {=IF('Raw Data'!C5="",_xlfn.REGEXEXTRACT(CELL("address",'Raw Data'!C5),"\$([A-Z]+)\$[0-9]+"),"")} -> $C$5 | D5: {=IF('Raw Data'!D5="",_xlfn.REGEXEXTRACT(CELL("address",'Raw Data'!D5),"\$([A-Z]+)\$[0-9]+"),"")} -> $D$5 | E5: {=IF('Raw Data'!E5="",_xlfn.REGEXEXTRACT(CELL("address",'Raw Data'!E5),"\$([A-Z]+)\$[0-9]+"),"")} -> $E$5 | F5: {=IF('Raw Data'!F5="",_xlfn.REGEXEXTRACT(CELL("address",'Raw Data'!F5),"\$([A-Z]+)\$[0-9]+"),"")} -> $F$5 | G5: {=IF('Raw Data'!G5="",_xlfn.REGEXEXTRACT(CELL("address",'Raw Data'!G5),"\$([A-Z]+)\$[0-9]+"),"")} -> $G$5 | H5: {=IF('Raw Data'!H5="",_xlfn.REGEXEXTRACT(CELL("address",'Raw Data'!H5),"\$([A-Z]+)\$[0-9]+"),"")} -> $H$5 | I5: {=IF('Raw Data'!I5="",_xlfn.REGEXEXTRACT(CELL("address",'Raw Data'!I5),"\$([A-Z]+)\$[0-9]+"),"")} -> $I$5
B6: {=IF('Raw Data'!B6="",_xlfn.REGEXEXTRACT(CELL("address",'Raw Data'!B6),"\$([A-Z]+)\$[0-9]+"),"")} -> $B$6 | C6: {=IF('Raw Data'!C6="",_xlfn.REGEXEXTRACT(CELL("address",'Raw Data'!C6),"\$([A-Z]+)\$[0-9]+"),"")} -> $C$6 | D6: {=IF('Raw Data'!D6="",_xlfn.REGEXEXTRACT(CELL("address",'Raw Data'!D6),"\$([A-Z]+)\$[0-9]+"),"")} -> $D$6 | E6: {=IF('Raw Data'!E6="",_xlfn.REGEXEXTRACT(CELL("address",'Raw Data'!E6),"\$([A-Z]+)\$[0-9]+"),"")} -> $E$6 | F6: {=IF('Raw Data'!F6="",_xlfn.REGEXEXTRACT(CELL("address",'Raw Data'!F6),"\$([A-Z]+)\$[0-9]+"),"")} -> $F$6 | G6: {=IF('Raw Data'!G6="",_xlfn.REGEXEXTRACT(CELL("address",'Raw Data'!G6),"\$([A-Z]+)\$[0-9]+"),"")} -> $G$6 | H6: {=IF('Raw Data'!H6="",_xlfn.REGEXEXTRACT(CELL("address",'Raw Data'!H6),"\$([A-Z]+)\$[0-9]+"),"")} -> $H$6 | I6: {=IF('Raw Data'!I6="",_xlfn.REGEXEXTRACT(CELL("address",'Raw Data'!I6),"\$([A-Z]+)\$[0-9]+"),"")} -> $I$6
B7: {=IF('Raw Data'!B7="",_xlfn.REGEXEXTRACT(CELL("address",'Raw Data'!B7),"\$([A-Z]+)\$[0-9]+"),"")} -> $B$7 | C7: {=IF('Raw Data'!C7="",_xlfn.REGEXEXTRACT(CELL("address",'Raw Data'!C7),"\$([A-Z]+)\$[0-9]+"),"")} -> $C$7 | D7: {=IF('Raw Data'!D7="",_xlfn.REGEXEXTRACT(CELL("address",'Raw Data'!D7),"\$([A-Z]+)\$[0-9]+"),"")} -> $D$7 | E7: {=IF('Raw Data'!E7="",_xlfn.REGEXEXTRACT(CELL("address",'Raw Data'!E7),"\$([A-Z]+)\$[0-9]+"),"")} -> $E$7 | F7: {=IF('Raw Data'!F7="",_xlfn.REGEXEXTRACT(CELL("address",'Raw Data'!F7),"\$([A-Z]+)\$[0-9]+"),"")} -> $F$7 | G7: {=IF('Raw Data'!G7="",_xlfn.REGEXEXTRACT(CELL("address",'Raw Data'!G7),"\$([A-Z]+)\$[0-9]+"),"")} -> $G$7 | H7: {=IF('Raw Data'!H7="",_xlfn.REGEXEXTRACT(CELL("address",'Raw Data'!H7),"\$([A-Z]+)\$[0-9]+"),"")} -> $H$7 | I7: {=IF('Raw Data'!I7="",_xlfn.REGEXEXTRACT(CELL("address",'Raw Data'!I7),"\$([A-Z]+)\$[0-9]+"),"")} -> $I$7
B8: {=IF('Raw Data'!B8="",_xlfn.REGEXEXTRACT(CELL("address",'Raw Data'!B8),"\$([A-Z]+)\$[0-9]+"),"")} -> $B$8 | C8: {=IF('Raw Data'!C8="",_xlfn.REGEXEXTRACT(CELL("address",'Raw Data'!C8),"\$([A-Z]+)\$[0-9]+"),"")} -> $C$8 | D8: {=IF('Raw Data'!D8="",_xlfn.REGEXEXTRACT(CELL("address",'Raw Data'!D8),"\$([A-Z]+)\$[0-9]+"),"")} -> $D$8 | E8: {=IF('Raw Data'!E8="",_xlfn.REGEXEXTRACT(CELL("address",'Raw Data'!E8),"\$([A-Z]+)\$[0-9]+"),"")} -> $E$8 | F8: {=IF('Raw Data'!F8="",_xlfn.REGEXEXTRACT(CELL("address",'Raw Data'!F8),"\$([A-Z]+)\$[0-9]+"),"")} -> $F$8 | G8: {=IF('Raw Data'!G8="",_xlfn.REGEXEXTRACT(CELL("address",'Raw Data'!G8),"\$([A-Z]+)\$[0-9]+"),"")} -> $G$8 | H8: {=IF('Raw Data'!H8="",_xlfn.REGEXEXTRACT(CELL("address",'Raw Data'!H8),"\$([A-Z]+)\$[0-9]+"),"")} -> $H$8 | I8: {=IF('Raw Data'!I8="",_xlfn.REGEXEXTRACT(CELL("address",'Raw Data'!I8),"\$([A-Z]+)\$[0-9]+"),"")} -> $I$8
B9: {=IF('Raw Data'!#REF!="",_xlfn.REGEXEXTRACT(CELL("address",'Raw Data'!#REF!),"\$([A-Z]+)\$[0-9]+"),"")} -> #REF! | C9: {=IF('Raw Data'!#REF!="",_xlfn.REGEXEXTRACT(CELL("address",'Raw Data'!#REF!),"\$([A-Z]+)\$[0-9]+"),"")} -> #REF! | D9: {=IF('Raw Data'!#REF!="",_xlfn.REGEXEXTRACT(CELL("address",'Raw Data'!#REF!),"\$([A-Z]+)\$[0-9]+"),"")} -> #REF! | E9: {=IF('Raw Data'!#REF!="",_xlfn.REGEXEXTRACT(CELL("address",'Raw Data'!#REF!),"\$([A-Z]+)\$[0-9]+"),"")} -> #REF! | F9: {=IF('Raw Data'!#REF!="",_xlfn.REGEXEXTRACT(CELL("address",'Raw Data'!#REF!),"\$([A-Z]+)\$[0-9]+"),"")} -> #REF! | G9: {=IF('Raw Data'!#REF!="",_xlfn.REGEXEXTRACT(CELL("address",'Raw Data'!#REF!),"\$([A-Z]+)\$[0-9]+"),"")} -> #REF! | H9: {=IF('Raw Data'!#REF!="",_xlfn.REGEXEXTRACT(CELL("address",'Raw Data'!#REF!),"\$([A-Z]+)\$[0-9]+"),"")} -> #REF! | I9: {=IF('Raw Data'!#REF!="",_xlfn.REGEXEXTRACT(CELL("address",'Raw Data'!#REF!),"\$([A-Z]+)\$[0-9]+"),"")} -> #REF!
B10: {=IF('Raw Data'!B10="",_xlfn.REGEXEXTRACT(CELL("address",'Raw Data'!B10),"\$([A-Z]+)\$[0-9]+"),"")} -> $B$10 | C10: {=IF('Raw Data'!C10="",_xlfn.REGEXEXTRACT(CELL("address",'Raw Data'!C10),"\$([A-Z]+)\$[0-9]+"),"")} | D10: {=IF('Raw Data'!D10="",_xlfn.REGEXEXTRACT(CELL("address",'Raw Data'!D10),"\$([A-Z]+)\$[0-9]+"),"")} | E10: {=IF('Raw Data'!E10="",_xlfn.REGEXEXTRACT(CELL("address",'Raw Data'!E10),"\$([A-Z]+)\$[0-9]+"),"")} | F10: {=IF('Raw Data'!F10="",_xlfn.REGEXEXTRACT(CELL("address",'Raw Data'!F10),"\$([A-Z]+)\$[0-9]+"),"")} | G10: {=IF('Raw Data'!G10="",_xlfn.REGEXEXTRACT(CELL("address",'Raw Data'!G10),"\$([A-Z]+)\$[0-9]+"),"")} | H10: {=IF('Raw Data'!H10="",_xlfn.REGEXEXTRACT(CELL("address",'Raw Data'!H10),"\$([A-Z]+)\$[0-9]+"),"")} | I10: {=IF('Raw Data'!I10="",_xlfn.REGEXEXTRACT(CELL("address",'Raw Data'!I10),"\$([A-Z]+)\$[0-9]+"),"")}
B11: {=IF('Raw Data'!B11="",_xlfn.REGEXEXTRACT(CELL("address",'Raw Data'!B11),"\$([A-Z]+)\$[0-9]+"),"")} -> $B$11 | C11: {=IF('Raw Data'!C11="",_xlfn.REGEXEXTRACT(CELL("address",'Raw Data'!C11),"\$([A-Z]+)\$[0-9]+"),"")} | D11: {=IF('Raw Data'!D11="",_xlfn.REGEXEXTRACT(CELL("address",'Raw Data'!D11),"\$([A-Z]+)\$[0-9]+"),"")} | E11: {=IF('Raw Data'!E11="",_xlfn.REGEXEXTRACT(CELL("address",'Raw Data'!E11),"\$([A-Z]+)\$[0-9]+"),"")} | F11: {=IF('Raw Data'!F11="",_xlfn.REGEXEXTRACT(CELL("address",'Raw Data'!F11),"\$([A-Z]+)\$[0-9]+"),"")} | G11: {=IF('Raw Data'!G11="",_xlfn.REGEXEXTRACT(CELL("address",'Raw Data'!G11),"\$([A-Z]+)\$[0-9]+"),"")} | H11: {=IF('Raw Data'!H11="",_xlfn.REGEXEXTRACT(CELL("address",'Raw Data'!H11),"\$([A-Z]+)\$[0-9]+"),"")} | I11: {=IF('Raw Data'!I11="",_xlfn.REGEXEXTRACT(CELL("address",'Raw Data'!I11),"\$([A-Z]+)\$[0-9]+"),"")}
B12: {=IF('Raw Data'!B12="",_xlfn.REGEXEXTRACT(CELL("address",'Raw Data'!B12),"\$([A-Z]+)\$[0-9]+"),"")} -> $B$12 | C12: {=IF('Raw Data'!C12="",_xlfn.REGEXEXTRACT(CELL("address",'Raw Data'!C12),"\$([A-Z]+)\$[0-9]+"),"")} | D12: {=IF('Raw Data'!D12="",_xlfn.REGEXEXTRACT(CELL("address",'Raw Data'!D12),"\$([A-Z]+)\$[0-9]+"),"")} | E12: {=IF('Raw Data'!E12="",_xlfn.REGEXEXTRACT(CELL("address",'Raw Data'!E12),"\$([A-Z]+)\$[0-9]+"),"")} | F12: {=IF('Raw Data'!F12="",_xlfn.REGEXEXTRACT(CELL("address",'Raw Data'!F12),"\$([A-Z]+)\$[0-9]+"),"")} | G12: {=IF('Raw Data'!G12="",_xlfn.REGEXEXTRACT(CELL("address",'Raw Data'!G12),"\$([A-Z]+)\$[0-9]+"),"")} | H12: {=IF('Raw Data'!H12="",_xlfn.REGEXEXTRACT(CELL("address",'Raw Data'!H12),"\$([A-Z]+)\$[0-9]+"),"")} | I12: {=IF('Raw Data'!I12="",_xlfn.REGEXEXTRACT(CELL("address",'Raw Data'!I12),"\$([A-Z]+)\$[0-9]+"),"")}
B13: {=IF('Raw Data'!B13="",_xlfn.REGEXEXTRACT(CELL("address",'Raw Data'!B13),"\$([A-Z]+)\$[0-9]+"),"")} -> $B$13 | C13: {=IF('Raw Data'!C13="",_xlfn.REGEXEXTRACT(CELL("address",'Raw Data'!C13),"\$([A-Z]+)\$[0-9]+"),"")} | D13: {=IF('Raw Data'!D13="",_xlfn.REGEXEXTRACT(CELL("address",'Raw Data'!D13),"\$([A-Z]+)\$[0-9]+"),"")} | E13: {=IF('Raw Data'!E13="",_xlfn.REGEXEXTRACT(CELL("address",'Raw Data'!E13),"\$([A-Z]+)\$[0-9]+"),"")} | F13: {=IF('Raw Data'!F13="",_xlfn.REGEXEXTRACT(CELL("address",'Raw Data'!F13),"\$([A-Z]+)\$[0-9]+"),"")} | G13: {=IF('Raw Data'!G13="",_xlfn.REGEXEXTRACT(CELL("address",'Raw Data'!G13),"\$([A-Z]+)\$[0-9]+"),"")} | H13: {=IF('Raw Data'!H13="",_xlfn.REGEXEXTRACT(CELL("address",'Raw Data'!H13),"\$([A-Z]+)\$[0-9]+"),"")} | I13: {=IF('Raw Data'!I13="",_xlfn.REGEXEXTRACT(CELL("address",'Raw Data'!I13),"\$([A-Z]+)\$[0-9]+"),"")}
B14: {=IF('Raw Data'!B14="",_xlfn.REGEXEXTRACT(CELL("address",'Raw Data'!B14),"\$([A-Z]+)\$[0-9]+"),"")} -> $B$14 | C14: {=IF('Raw Data'!C14="",_xlfn.REGEXEXTRACT(CELL("address",'Raw Data'!C14),"\$([A-Z]+)\$[0-9]+"),"")} | D14: {=IF('Raw Data'!D14="",_xlfn.REGEXEXTRACT(CELL("address",'Raw Data'!D14),"\$([A-Z]+)\$[0-9]+"),"")} | E14: {=IF('Raw Data'!E14="",_xlfn.REGEXEXTRACT(CELL("address",'Raw Data'!E14),"\$([A-Z]+)\$[0-9]+"),"")} | F14: {=IF('Raw Data'!F14="",_xlfn.REGEXEXTRACT(CELL("address",'Raw Data'!F14),"\$([A-Z]+)\$[0-9]+"),"")} | G14: {=IF('Raw Data'!G14="",_xlfn.REGEXEXTRACT(CELL("address",'Raw Data'!G14),"\$([A-Z]+)\$[0-9]+"),"")} | H14: {=IF('Raw Data'!H14="",_xlfn.REGEXEXTRACT(CELL("address",'Raw Data'!H14),"\$([A-Z]+)\$[0-9]+"),"")} | I14: {=IF('Raw Data'!I14="",_xlfn.REGEXEXTRACT(CELL("address",'Raw Data'!I14),"\$([A-Z]+)\$[0-9]+"),"")}
B15: {=IF('Raw Data'!B15="",_xlfn.REGEXEXTRACT(CELL("address",'Raw Data'!B15),"\$([A-Z]+)\$[0-9]+"),"")} -> $B$15 | C15: {=IF('Raw Data'!C15="",_xlfn.REGEXEXTRACT(CELL("address",'Raw Data'!C15),"\$([A-Z]+)\$[0-9]+"),"")} | D15: {=IF('Raw Data'!D15="",_xlfn.REGEXEXTRACT(CELL("address",'Raw Data'!D15),"\$([A-Z]+)\$[0-9]+"),"")} | E15: {=IF('Raw Data'!E15="",_xlfn.REGEXEXTRACT(CELL("address",'Raw Data'!E15),"\$([A-Z]+)\$[0-9]+"),"")} | F15: {=IF('Raw Data'!F15="",_xlfn.REGEXEXTRACT(CELL("address",'Raw Data'!F15),"\$([A-Z]+)\$[0-9]+"),"")} | G15: {=IF('Raw Data'!G15="",_xlfn.REGEXEXTRACT(CELL("address",'Raw Data'!G15),"\$([A-Z]+)\$[0-9]+"),"")} | H15: {=IF('Raw Data'!H15="",_xlfn.REGEXEXTRACT(CELL("address",'Raw Data'!H15),"\$([A-Z]+)\$[0-9]+"),"")} | I15: {=IF('Raw Data'!I15="",_xlfn.REGEXEXTRACT(CELL("address",'Raw Data'!I15),"\$([A-Z]+)\$[0-9]+"),"")}
B16: {=IF('Raw Data'!B16="",_xlfn.REGEXEXTRACT(CELL("address",'Raw Data'!B16),"\$([A-Z]+)\$[0-9]+"),"")} -> $B$16 | C16: {=IF('Raw Data'!C16="",_xlfn.REGEXEXTRACT(CELL("address",'Raw Data'!C16),"\$([A-Z]+)\$[0-9]+"),"")} | D16: {=IF('Raw Data'!D16="",_xlfn.REGEXEXTRACT(CELL("address",'Raw Data'!D16),"\$([A-Z]+)\$[0-9]+"),"")} | E16: {=IF('Raw Data'!E16="",_xlfn.REGEXEXTRACT(CELL("address",'Raw Data'!E16),"\$([A-Z]+)\$[0-9]+"),"")} | F16: {=IF('Raw Data'!F16="",_xlfn.REGEXEXTRACT(CELL("address",'Raw Data'!F16),"\$([A-Z]+)\$[0-9]+"),"")} | G16: {=IF('Raw Data'!G16="",_xlfn.REGEXEXTRACT(CELL("address",'Raw Data'!G16),"\$([A-Z]+)\$[0-9]+"),"")} | H16: {=IF('Raw Data'!H16="",_xlfn.REGEXEXTRACT(CELL("address",'Raw Data'!H16),"\$([A-Z]+)\$[0-9]+"),"")} | I16: {=IF('Raw Data'!I16="",_xlfn.REGEXEXTRACT(CELL("address",'Raw Data'!I16),"\$([A-Z]+)\$[0-9]+"),"")}
B17: {=IF('Raw Data'!B17="",_xlfn.REGEXEXTRACT(CELL("address",'Raw Data'!B17),"\$([A-Z]+)\$[0-9]+"),"")} -> $B$17 | C17: {=IF('Raw Data'!C17="",_xlfn.REGEXEXTRACT(CELL("address",'Raw Data'!C17),"\$([A-Z]+)\$[0-9]+"),"")} | D17: {=IF('Raw Data'!D17="",_xlfn.REGEXEXTRACT(CELL("address",'Raw Data'!D17),"\$([A-Z]+)\$[0-9]+"),"")} | E17: {=IF('Raw Data'!E17="",_xlfn.REGEXEXTRACT(CELL("address",'Raw Data'!E17),"\$([A-Z]+)\$[0-9]+"),"")} | F17: {=IF('Raw Data'!F17="",_xlfn.REGEXEXTRACT(CELL("address",'Raw Data'!F17),"\$([A-Z]+)\$[0-9]+"),"")} | G17: {=IF('Raw Data'!G17="",_xlfn.REGEXEXTRACT(CELL("address",'Raw Data'!G17),"\$([A-Z]+)\$[0-9]+"),"")} | H17: {=IF('Raw Data'!H17="",_xlfn.REGEXEXTRACT(CELL("address",'Raw Data'!H17),"\$([A-Z]+)\$[0-9]+"),"")} | I17: {=IF('Raw Data'!I17="",_xlfn.REGEXEXTRACT(CELL("address",'Raw Data'!I17),"\$([A-Z]+)\$[0-9]+"),"")}
B18: {=IF('Raw Data'!B18="",_xlfn.REGEXEXTRACT(CELL("address",'Raw Data'!B18),"\$([A-Z]+)\$[0-9]+"),"")} -> $B$18 | C18: {=IF('Raw Data'!C18="",_xlfn.REGEXEXTRACT(CELL("address",'Raw Data'!C18),"\$([A-Z]+)\$[0-9]+"),"")} | D18: {=IF('Raw Data'!D18="",_xlfn.REGEXEXTRACT(CELL("address",'Raw Data'!D18),"\$([A-Z]+)\$[0-9]+"),"")} | E18: {=IF('Raw Data'!E18="",_xlfn.REGEXEXTRACT(CELL("address",'Raw Data'!E18),"\$([A-Z]+)\$[0-9]+"),"")} | F18: {=IF('Raw Data'!F18="",_xlfn.REGEXEXTRACT(CELL("address",'Raw Data'!F18),"\$([A-Z]+)\$[0-9]+"),"")} | G18: {=IF('Raw Data'!G18="",_xlfn.REGEXEXTRACT(CELL("address",'Raw Data'!G18),"\$([A-Z]+)\$[0-9]+"),"")} | H18: {=IF('Raw Data'!H18="",_xlfn.REGEXEXTRACT(CELL("address",'Raw Data'!H18),"\$([A-Z]+)\$[0-9]+"),"")} | I18: {=IF('Raw Data'!I18="",_xlfn.REGEXEXTRACT(CELL("address",'Raw Data'!I18),"\$([A-Z]+)\$[0-9]+"),"")}
B19: {=IF('Raw Data'!B19="",_xlfn.REGEXEXTRACT(CELL("address",'Raw Data'!B19),"\$([A-Z]+)\$[0-9]+"),"")} -> $B$19 | C19: {=IF('Raw Data'!C19="",_xlfn.REGEXEXTRACT(CELL("address",'Raw Data'!C19),"\$([A-Z]+)\$[0-9]+"),"")} | D19: {=IF('Raw Data'!D19="",_xlfn.REGEXEXTRACT(CELL("address",'Raw Data'!D19),"\$([A-Z]+)\$[0-9]+"),"")} | E19: {=IF('Raw Data'!E19="",_xlfn.REGEXEXTRACT(CELL("address",'Raw Data'!E19),"\$([A-Z]+)\$[0-9]+"),"")} | F19: {=IF('Raw Data'!F19="",_xlfn.REGEXEXTRACT(CELL("address",'Raw Data'!F19),"\$([A-Z]+)\$[0-9]+"),"")} | G19: {=IF('Raw Data'!G19="",_xlfn.REGEXEXTRACT(CELL("address",'Raw Data'!G19),"\$([A-Z]+)\$[0-9]+"),"")} | H19: {=IF('Raw Data'!H19="",_xlfn.REGEXEXTRACT(CELL("address",'Raw Data'!H19),"\$([A-Z]+)\$[0-9]+"),"")} | I19: {=IF('Raw Data'!I19="",_xlfn.REGEXEXTRACT(CELL("address",'Raw Data'!I19),"\$([A-Z]+)\$[0-9]+"),"")}
B20: {=IF('Raw Data'!B20="",_xlfn.REGEXEXTRACT(CELL("address",'Raw Data'!B20),"\$([A-Z]+)\$[0-9]+"),"")} -> $B$20 | C20: {=IF('Raw Data'!C20="",_xlfn.REGEXEXTRACT(CELL("address",'Raw Data'!C20),"\$([A-Z]+)\$[0-9]+"),"")} | D20: {=IF('Raw Data'!D20="",_xlfn.REGEXEXTRACT(CELL("address",'Raw Data'!D20),"\$([A-Z]+)\$[0-9]+"),"")} | E20: {=IF('Raw Data'!E20="",_xlfn.REGEXEXTRACT(CELL("address",'Raw Data'!E20),"\$([A-Z]+)\$[0-9]+"),"")} | F20: {=IF('Raw Data'!F20="",_xlfn.REGEXEXTRACT(CELL("address",'Raw Data'!F20),"\$([A-Z]+)\$[0-9]+"),"")} | G20: {=IF('Raw Data'!G20="",_xlfn.REGEXEXTRACT(CELL("address",'Raw Data'!G20),"\$([A-Z]+)\$[0-9]+"),"")} | H20: {=IF('Raw Data'!H20="",_xlfn.REGEXEXTRACT(CELL("address",'Raw Data'!H20),"\$([A-Z]+)\$[0-9]+"),"")} | I20: {=IF('Raw Data'!I20="",_xlfn.REGEXEXTRACT(CELL("address",'Raw Data'!I20),"\$([A-Z]+)\$[0-9]+"),"")}
B21: {=IF('Raw Data'!B21="",_xlfn.REGEXEXTRACT(CELL("address",'Raw Data'!B21),"\$([A-Z]+)\$[0-9]+"),"")} -> $B$21 | C21: {=IF('Raw Data'!C21="",_xlfn.REGEXEXTRACT(CELL("address",'Raw Data'!C21),"\$([A-Z]+)\$[0-9]+"),"")} | D21: {=IF('Raw Data'!D21="",_xlfn.REGEXEXTRACT(CELL("address",'Raw Data'!D21),"\$([A-Z]+)\$[0-9]+"),"")} | E21: {=IF('Raw Data'!E21="",_xlfn.REGEXEXTRACT(CELL("address",'Raw Data'!E21),"\$([A-Z]+)\$[0-9]+"),"")} | F21: {=IF('Raw Data'!F21="",_xlfn.REGEXEXTRACT(CELL("address",'Raw Data'!F21),"\$([A-Z]+)\$[0-9]+"),"")} | G21: {=IF('Raw Data'!G21="",_xlfn.REGEXEXTRACT(CELL("address",'Raw Data'!G21),"\$([A-Z]+)\$[0-9]+"),"")} | H21: {=IF('Raw Data'!H21="",_xlfn.REGEXEXTRACT(CELL("address",'Raw Data'!H21),"\$([A-Z]+)\$[0-9]+"),"")} | I21: {=IF('Raw Data'!I21="",_xlfn.REGEXEXTRACT(CELL("address",'Raw Data'!I21),"\$([A-Z]+)\$[0-9]+"),"")}
... B300: {=IF('Raw Data'!B300="",_xlfn.REGEXEXTRACT(CELL("address",'Raw Data'!B300),"\$([A-Z]+)\$[0-9]+"),"")} -> $B$300 | C300: {=IF('Raw Data'!C300="",_xlfn.REGEXEXTRACT(CELL("address",'Raw Data'!C300),"\$([A-Z]+)\$[0-9]+"),"")} | D300: {=IF('Raw Data'!D300="",_xlfn.REGEXEXTRACT(CELL("address",'Raw Data'!D300),"\$([A-Z]+)\$[0-9]+"),"")} | E300: {=IF('Raw Data'!E300="",_xlfn.REGEXEXTRACT(CELL("address",'Raw Data'!E300),"\$([A-Z]+)\$[0-9]+"),"")} | F300: {=IF('Raw Data'!F300="",_xlfn.REGEXEXTRACT(CELL("address",'Raw Data'!F300),"\$([A-Z]+)\$[0-9]+"),"")} | G300: {=IF('Raw Data'!G300="",_xlfn.REGEXEXTRACT(CELL("address",'Raw Data'!G300),"\$([A-Z]+)\$[0-9]+"),"")} | H300: {=IF('Raw Data'!H300="",_xlfn.REGEXEXTRACT(CELL("address",'Raw Data'!H300),"\$([A-Z]+)\$[0-9]+"),"")} | I300: {=IF('Raw Data'!I300="",_xlfn.REGEXEXTRACT(CELL("address",'Raw Data'!I300),"\$([A-Z]+)\$[0-9]+"),"")}
